{
	"CapturedObjects" : 
	[
		{
			"Absolute Acceleration X" : 0.30610084533691406,
			"Absolute Acceleration Y" : -0.88415902853012085,
			"Absolute Acceleration Z" : 0.011337384581565857,
			"Absolute Velocity X" : 23.811676025390625,
			"Absolute Velocity Y" : 0.55448836088180542,
			"Absolute Velocity Z" : -0.20357781648635864,
			"ActorName" : "TRUCK 00",
			"BoundingBox3D Extent X" : 6.6553831100463867,
			"BoundingBox3D Extent Y" : 3.0,
			"BoundingBox3D Extent Z" : 2.1005990505218506,
			"BoundingBox3D Orientation Quat W" : 0.9999086856842041,
			"BoundingBox3D Orientation Quat X" : -0.007094639353454113,
			"BoundingBox3D Orientation Quat Y" : 0.003369324142113328,
			"BoundingBox3D Orientation Quat Z" : 0.010741572827100754,
			"BoundingBox3D Origin X" : -9.9619894027709961,
			"BoundingBox3D Origin Y" : -3.5857236385345459,
			"BoundingBox3D Origin Z" : 1.0902721881866455,
			"ObjectId" : 0,
			"ObjectType" : "TRUCK",
			"Occluded" : 0.0,
			"Relative Acceleration X" : 0.28472423553466797,
			"Relative Acceleration Y" : 0.16123813390731812,
			"Relative Acceleration Z" : 0.0058132447302341461,
			"Relative Velocity X" : -3.9115982055664062,
			"Relative Velocity Y" : 0.20671179890632629,
			"Relative Velocity Z" : 0.044307611882686615,
			"Truncated" : 0
		},
		{
			"Absolute Acceleration X" : 0.13158035278320312,
			"Absolute Acceleration Y" : -1.2536303997039795,
			"Absolute Acceleration Z" : 0.07015247642993927,
			"Absolute Velocity X" : 28.225519180297852,
			"Absolute Velocity Y" : 0.97125542163848877,
			"Absolute Velocity Z" : -0.26929038763046265,
			"ActorName" : "CAR 02",
			"BoundingBox3D Extent X" : 4.3166317939758301,
			"BoundingBox3D Extent Y" : 2.0303733348846436,
			"BoundingBox3D Extent Z" : 1.4497169256210327,
			"BoundingBox3D Orientation Quat W" : 0.99978488683700562,
			"BoundingBox3D Orientation Quat X" : 0.0080280900001525879,
			"BoundingBox3D Orientation Quat Y" : 0.0052971835248172283,
			"BoundingBox3D Orientation Quat Z" : 0.018166711553931236,
			"BoundingBox3D Origin X" : -22.135637283325195,
			"BoundingBox3D Origin Y" : -0.13470636308193207,
			"BoundingBox3D Origin Z" : 0.84913736581802368,
			"ObjectId" : 2,
			"ObjectType" : "CAR",
			"Occluded" : 0.0,
			"Relative Acceleration X" : 0.10301443934440613,
			"Relative Acceleration Y" : 0.24369770288467407,
			"Relative Acceleration Z" : 0.07490529865026474,
			"Relative Velocity X" : 0.32510241866111755,
			"Relative Velocity Y" : -0.0041723698377609253,
			"Relative Velocity Z" : 0.0034684357233345509,
			"Truncated" : 0
		},
		{
			"Absolute Acceleration X" : 0.41564750671386719,
			"Absolute Acceleration Y" : -0.70233124494552612,
			"Absolute Acceleration Z" : 0.03993813693523407,
			"Absolute Velocity X" : 22.144842147827148,
			"Absolute Velocity Y" : 0.91576546430587769,
			"Absolute Velocity Z" : -0.20530080795288086,
			"ActorName" : "CAR 03",
			"BoundingBox3D Extent X" : 5.0730719566345215,
			"BoundingBox3D Extent Y" : 2.2716178894042969,
			"BoundingBox3D Extent Z" : 1.5020607709884644,
			"BoundingBox3D Orientation Quat W" : 0.99930143356323242,
			"BoundingBox3D Orientation Quat X" : -0.0068937754258513451,
			"BoundingBox3D Orientation Quat Y" : 0.0041035953909158707,
			"BoundingBox3D Orientation Quat Z" : 0.036385029554367065,
			"BoundingBox3D Origin X" : -29.199493408203125,
			"BoundingBox3D Origin Y" : -4.2370986938476562,
			"BoundingBox3D Origin Z" : 0.95649856328964233,
			"ObjectId" : 3,
			"ObjectType" : "CAR",
			"Occluded" : 0.0,
			"Relative Acceleration X" : 0.39356565475463867,
			"Relative Acceleration Y" : 0.22879526019096375,
			"Relative Acceleration Z" : 0.097901120781898499,
			"Relative Velocity X" : -5.5451607704162598,
			"Relative Velocity Y" : -0.4191836416721344,
			"Relative Velocity Z" : 0.073778755962848663,
			"Truncated" : 0
		},
		{
			"Absolute Acceleration X" : -0.083791732788085938,
			"Absolute Acceleration Y" : -1.3874243497848511,
			"Absolute Acceleration Z" : 0.09208303689956665,
			"Absolute Velocity X" : 28.90705680847168,
			"Absolute Velocity Y" : 1.8473705053329468,
			"Absolute Velocity Z" : -0.31513175368309021,
			"ActorName" : "CAR 08",
			"BoundingBox3D Extent X" : 4.2066030502319336,
			"BoundingBox3D Extent Y" : 1.8615398406982422,
			"BoundingBox3D Extent Z" : 1.6073957681655884,
			"BoundingBox3D Orientation Quat W" : 0.9992821216583252,
			"BoundingBox3D Orientation Quat X" : 0.0051274970173835754,
			"BoundingBox3D Orientation Quat Y" : 0.0064841541461646557,
			"BoundingBox3D Orientation Quat Z" : 0.036679886281490326,
			"BoundingBox3D Origin X" : -35.65283203125,
			"BoundingBox3D Origin Y" : -0.28271904587745667,
			"BoundingBox3D Origin Z" : 1.1099451780319214,
			"ObjectId" : 8,
			"ObjectType" : "CAR",
			"Occluded" : 0.0,
			"Relative Acceleration X" : -0.1657789945602417,
			"Relative Acceleration Y" : 0.20099975168704987,
			"Relative Acceleration Z" : 0.13321028649806976,
			"Relative Velocity X" : 1.0178000926971436,
			"Relative Velocity Y" : 0.17222143709659576,
			"Relative Velocity Z" : -0.020086146891117096,
			"Truncated" : 0
		},
		{
			"Absolute Acceleration X" : -0.090274810791015625,
			"Absolute Acceleration Y" : -1.0724549293518066,
			"Absolute Acceleration Z" : 0.042764775454998016,
			"Absolute Velocity X" : 23.073495864868164,
			"Absolute Velocity Y" : -5.7313475608825684,
			"Absolute Velocity Z" : 0.051092356443405151,
			"ActorName" : "CAR 12",
			"BoundingBox3D Extent X" : 4.0999999046325684,
			"BoundingBox3D Extent Y" : 1.8652873039245605,
			"BoundingBox3D Extent Z" : 1.5670369863510132,
			"BoundingBox3D Orientation Quat W" : -0.99275261163711548,
			"BoundingBox3D Orientation Quat X" : -0.0041056638583540916,
			"BoundingBox3D Orientation Quat Y" : 0.0018530002562329173,
			"BoundingBox3D Orientation Quat Z" : 0.12006623297929764,
			"BoundingBox3D Origin X" : 135.62333679199219,
			"BoundingBox3D Origin Y" : -23.244132995605469,
			"BoundingBox3D Origin Z" : 0.29863673448562622,
			"ObjectId" : 12,
			"ObjectType" : "CAR",
			"Occluded" : 0.0,
			"Relative Acceleration X" : 0.096786737442016602,
			"Relative Acceleration Y" : -0.36560893058776855,
			"Relative Acceleration Z" : -0.3568076491355896,
			"Relative Velocity X" : -3.6361544132232666,
			"Relative Velocity Y" : 1.3981423377990723,
			"Relative Velocity Z" : 0.017509046941995621,
			"Truncated" : 0
		},
		{
			"Absolute Acceleration X" : -0.18496131896972656,
			"Absolute Acceleration Y" : -1.1732939481735229,
			"Absolute Acceleration Z" : 0.021286383271217346,
			"Absolute Velocity X" : 25.580123901367188,
			"Absolute Velocity Y" : -2.0053055286407471,
			"Absolute Velocity Z" : -0.12519392371177673,
			"ActorName" : "TRUCK 20",
			"BoundingBox3D Extent X" : 11.0,
			"BoundingBox3D Extent Y" : 2.7777366638183594,
			"BoundingBox3D Extent Z" : 3.5999290943145752,
			"BoundingBox3D Orientation Quat W" : -0.99931555986404419,
			"BoundingBox3D Orientation Quat X" : 0.0044964118860661983,
			"BoundingBox3D Orientation Quat Y" : -0.00166463537607342,
			"BoundingBox3D Orientation Quat Z" : 0.036622978746891022,
			"BoundingBox3D Origin X" : 42.043258666992188,
			"BoundingBox3D Origin Y" : -4.7583484649658203,
			"BoundingBox3D Origin Z" : 1.4923919439315796,
			"ObjectId" : 20,
			"ObjectType" : "TRUCK",
			"Occluded" : 0.0,
			"Relative Acceleration X" : -0.087690591812133789,
			"Relative Acceleration Y" : -0.063380539417266846,
			"Relative Acceleration Z" : -0.14027751982212067,
			"Relative Velocity X" : -2.0798485279083252,
			"Relative Velocity Y" : 0.3142145574092865,
			"Relative Velocity Z" : 0.032329022884368896,
			"Truncated" : 0
		},
		{
			"Absolute Acceleration X" : -0.14067459106445312,
			"Absolute Acceleration Y" : -0.63707876205444336,
			"Absolute Acceleration Z" : 0.047349750995635986,
			"Absolute Velocity X" : 27.763025283813477,
			"Absolute Velocity Y" : 2.91813063621521,
			"Absolute Velocity Z" : -0.38028517365455627,
			"ActorName" : "CAR 21",
			"BoundingBox3D Extent X" : 4.0999999046325684,
			"BoundingBox3D Extent Y" : 1.7430233955383301,
			"BoundingBox3D Extent Z" : 1.1256037950515747,
			"BoundingBox3D Orientation Quat W" : 0.99856650829315186,
			"BoundingBox3D Orientation Quat X" : -0.0037040151655673981,
			"BoundingBox3D Orientation Quat Y" : 0.0073318104259669781,
			"BoundingBox3D Orientation Quat Z" : 0.052785914391279221,
			"BoundingBox3D Origin X" : -64.731712341308594,
			"BoundingBox3D Origin Y" : -6.6840872764587402,
			"BoundingBox3D Origin Z" : 1.1092209815979004,
			"ObjectId" : 21,
			"ObjectType" : "CAR",
			"Occluded" : 0.0,
			"Relative Acceleration X" : -0.27993717789649963,
			"Relative Acceleration Y" : 0.91470921039581299,
			"Relative Acceleration Z" : 0.18397107720375061,
			"Relative Velocity X" : 0.19517256319522858,
			"Relative Velocity Y" : -0.24827490746974945,
			"Relative Velocity Z" : -0.048599649220705032,
			"Truncated" : 0
		},
		{
			"Absolute Acceleration X" : 0.03234100341796875,
			"Absolute Acceleration Y" : 0.44397306442260742,
			"Absolute Acceleration Z" : 0.036950826644897461,
			"Absolute Velocity X" : 24.726669311523438,
			"Absolute Velocity Y" : 5.9779152870178223,
			"Absolute Velocity Z" : -0.55902814865112305,
			"ActorName" : "CAR 24",
			"BoundingBox3D Extent X" : 4.0999999046325684,
			"BoundingBox3D Extent Y" : 2.5789535045623779,
			"BoundingBox3D Extent Z" : 1.211650013923645,
			"BoundingBox3D Orientation Quat W" : 0.99286389350891113,
			"BoundingBox3D Orientation Quat X" : -0.0090123536065220833,
			"BoundingBox3D Orientation Quat Y" : 0.0096414694562554359,
			"BoundingBox3D Orientation Quat Z" : 0.11846993863582611,
			"BoundingBox3D Origin X" : -172.29493713378906,
			"BoundingBox3D Origin Y" : -25.07942008972168,
			"BoundingBox3D Origin Z" : 3.017071008682251,
			"ObjectId" : 24,
			"ObjectType" : "CAR",
			"Occluded" : 0.0,
			"Relative Acceleration X" : -0.18339800834655762,
			"Relative Acceleration Y" : 1.9827464818954468,
			"Relative Acceleration Z" : 0.51503843069076538,
			"Relative Velocity X" : -1.9000213146209717,
			"Relative Velocity Y" : -2.7151978015899658,
			"Relative Velocity Z" : -0.083534255623817444,
			"Truncated" : 0
		},
		{
			"Absolute Acceleration X" : 0.10722392052412033,
			"Absolute Acceleration Y" : -0.21524782478809357,
			"Absolute Acceleration Z" : -0.13504263758659363,
			"Absolute Velocity X" : -24.895126342773438,
			"Absolute Velocity Y" : -2.2776803970336914,
			"Absolute Velocity Z" : 0.12538851797580719,
			"ActorName" : "CAR 26",
			"BoundingBox3D Extent X" : 4.4638233184814453,
			"BoundingBox3D Extent Y" : 1.8419269323348999,
			"BoundingBox3D Extent Z" : 1.8061484098434448,
			"BoundingBox3D Orientation Quat W" : -0.046843823045492172,
			"BoundingBox3D Orientation Quat X" : 0.003655862994492054,
			"BoundingBox3D Orientation Quat Y" : -8.0067125963978469e-05,
			"BoundingBox3D Orientation Quat Z" : 0.99888879060745239,
			"BoundingBox3D Origin X" : -82.171279907226562,
			"BoundingBox3D Origin Y" : 3.1070225238800049,
			"BoundingBox3D Origin Z" : 1.5155411958694458,
			"ObjectId" : 26,
			"ObjectType" : "CAR",
			"Occluded" : 0.0,
			"Relative Acceleration X" : 0.38083586096763611,
			"Relative Acceleration Y" : -4.3108282089233398,
			"Relative Acceleration Z" : -0.058074790984392166,
			"Relative Velocity X" : -52.954151153564453,
			"Relative Velocity Y" : -6.3193159103393555,
			"Relative Velocity Z" : 0.52431756258010864,
			"Truncated" : 0
		},
		{
			"Absolute Acceleration X" : 0.013433538377285004,
			"Absolute Acceleration Y" : -1.2657889127731323,
			"Absolute Acceleration Z" : -0.0080940304324030876,
			"Absolute Velocity X" : -28.419607162475586,
			"Absolute Velocity Y" : -3.0095870494842529,
			"Absolute Velocity Z" : 0.31170105934143066,
			"ActorName" : "CAR 27",
			"BoundingBox3D Extent X" : 4.0821447372436523,
			"BoundingBox3D Extent Y" : 1.8999999761581421,
			"BoundingBox3D Extent Z" : 1.6556839942932129,
			"BoundingBox3D Orientation Quat W" : -0.048554353415966034,
			"BoundingBox3D Orientation Quat X" : 0.0054758833721280098,
			"BoundingBox3D Orientation Quat Y" : -0.0030404843855649233,
			"BoundingBox3D Orientation Quat Z" : 0.99879729747772217,
			"BoundingBox3D Origin X" : -71.461105346679688,
			"BoundingBox3D Origin Y" : 11.092411994934082,
			"BoundingBox3D Origin Z" : 1.4743900299072266,
			"ObjectId" : 27,
			"ObjectType" : "CAR",
			"Occluded" : 0.0,
			"Relative Acceleration X" : 0.203351229429245,
			"Relative Acceleration Y" : -5.6515488624572754,
			"Relative Acceleration Z" : 0.068283654749393463,
			"Relative Velocity X" : -56.886863708496094,
			"Relative Velocity Y" : -6.5019612312316895,
			"Relative Velocity Z" : 0.7097887396812439,
			"Truncated" : 0
		},
		{
			"Absolute Acceleration X" : -0.15247344970703125,
			"Absolute Acceleration Y" : -1.4519733190536499,
			"Absolute Acceleration Z" : 0.040243238210678101,
			"Absolute Velocity X" : 28.993314743041992,
			"Absolute Velocity Y" : -1.8546477556228638,
			"Absolute Velocity Z" : -0.13248211145401001,
			"ActorName" : "CAR 28",
			"BoundingBox3D Extent X" : 4.5207657814025879,
			"BoundingBox3D Extent Y" : 2.0078058242797852,
			"BoundingBox3D Extent Z" : 2.0496177673339844,
			"BoundingBox3D Orientation Quat W" : -0.99936133623123169,
			"BoundingBox3D Orientation Quat X" : -0.0066039138473570347,
			"BoundingBox3D Orientation Quat Y" : -0.0018991659162566066,
			"BoundingBox3D Orientation Quat Z" : 0.035210181027650833,
			"BoundingBox3D Origin X" : 36.591323852539062,
			"BoundingBox3D Origin Y" : -0.67267966270446777,
			"BoundingBox3D Origin Z" : 0.7736397385597229,
			"ObjectId" : 28,
			"ObjectType" : "CAR",
			"Occluded" : 0.0,
			"Relative Acceleration X" : -0.048900723457336426,
			"Relative Acceleration Y" : -0.0031355395913124084,
			"Relative Acceleration Z" : -0.12656755745410919,
			"Relative Velocity X" : 1.121906042098999,
			"Relative Velocity Y" : 0.18538804352283478,
			"Relative Velocity Z" : 0.040416974574327469,
			"Truncated" : 0
		},
		{
			"Absolute Acceleration X" : 1.783227801322937,
			"Absolute Acceleration Y" : 0.12401077151298523,
			"Absolute Acceleration Z" : -0.0054939193651080132,
			"Absolute Velocity X" : -26.695674896240234,
			"Absolute Velocity Y" : -0.68454647064208984,
			"Absolute Velocity Z" : 0.27688845992088318,
			"ActorName" : "CAR 32",
			"BoundingBox3D Extent X" : 4.0999999046325684,
			"BoundingBox3D Extent Y" : 1.4898924827575684,
			"BoundingBox3D Extent Z" : 1.6733958721160889,
			"BoundingBox3D Orientation Quat W" : -0.0099082374945282936,
			"BoundingBox3D Orientation Quat X" : 0.005232411902397871,
			"BoundingBox3D Orientation Quat Y" : -0.0045299739576876163,
			"BoundingBox3D Orientation Quat Z" : 0.99992328882217407,
			"BoundingBox3D Origin X" : -51.535255432128906,
			"BoundingBox3D Origin Y" : 6.2966384887695312,
			"BoundingBox3D Origin Z" : 1.2214212417602539,
			"ObjectId" : 32,
			"ObjectType" : "CAR",
			"Occluded" : 0.0,
			"Relative Acceleration X" : 1.8312188386917114,
			"Relative Acceleration Y" : -4.1091656684875488,
			"Relative Acceleration Z" : 0.07575678825378418,
			"Relative Velocity X" : -54.923683166503906,
			"Relative Velocity Y" : -3.0623376369476318,
			"Relative Velocity Z" : 0.59212899208068848,
			"Truncated" : 0
		},
		{
			"Absolute Acceleration X" : 1.1057925224304199,
			"Absolute Acceleration Y" : 0.096878670156002045,
			"Absolute Acceleration Z" : 0.047999713569879532,
			"Absolute Velocity X" : -22.074914932250977,
			"Absolute Velocity Y" : -0.37696999311447144,
			"Absolute Velocity Z" : 0.24206404387950897,
			"ActorName" : "CAR 33",
			"BoundingBox3D Extent X" : 4.0999999046325684,
			"BoundingBox3D Extent Y" : 1.439570426940918,
			"BoundingBox3D Extent Z" : 1.5900218486785889,
			"BoundingBox3D Orientation Quat W" : -0.0079081626608967781,
			"BoundingBox3D Orientation Quat X" : 0.0058326371945440769,
			"BoundingBox3D Orientation Quat Y" : -9.6837982709985226e-05,
			"BoundingBox3D Orientation Quat Z" : 0.99994939565658569,
			"BoundingBox3D Origin X" : -34.885677337646484,
			"BoundingBox3D Origin Y" : 10.968747138977051,
			"BoundingBox3D Origin Z" : 1.0081113576889038,
			"ObjectId" : 33,
			"ObjectType" : "CAR",
			"Occluded" : 0.0,
			"Relative Acceleration X" : 1.0930615663528442,
			"Relative Acceleration Y" : -3.2462921142578125,
			"Relative Acceleration Z" : 0.19985771179199219,
			"Relative Velocity X" : -50.536655426025391,
			"Relative Velocity Y" : -1.9724090099334717,
			"Relative Velocity Z" : 0.57935208082199097,
			"Truncated" : 0
		},
		{
			"Absolute Acceleration X" : -0.089026786386966705,
			"Absolute Acceleration Y" : -0.71262526512145996,
			"Absolute Acceleration Z" : 0.057541839778423309,
			"Absolute Velocity X" : 25.988201141357422,
			"Absolute Velocity Y" : 4.9307765960693359,
			"Absolute Velocity Z" : -0.44869130849838257,
			"ActorName" : "CAR 34",
			"BoundingBox3D Extent X" : 4.0999999046325684,
			"BoundingBox3D Extent Y" : 1.3296940326690674,
			"BoundingBox3D Extent Z" : 0.59744054079055786,
			"BoundingBox3D Orientation Quat W" : 0.99492132663726807,
			"BoundingBox3D Orientation Quat X" : -0.0043340958654880524,
			"BoundingBox3D Orientation Quat Y" : 0.008449966087937355,
			"BoundingBox3D Orientation Quat Z" : 0.10018893331289291,
			"BoundingBox3D Origin X" : -114.02727508544922,
			"BoundingBox3D Origin Y" : -13.669887542724609,
			"BoundingBox3D Origin Z" : 1.5958881378173828,
			"ObjectId" : 34,
			"ObjectType" : "CAR",
			"Occluded" : 0.0,
			"Relative Acceleration X" : -0.19828848540782928,
			"Relative Acceleration Y" : -0.1001105010509491,
			"Relative Acceleration Z" : -0.27612859010696411,
			"Relative Velocity X" : -1.2116230726242065,
			"Relative Velocity Y" : -0.83849745988845825,
			"Relative Velocity Z" : -0.16766110062599182,
			"Truncated" : 0
		},
		{
			"Absolute Acceleration X" : 0.54362678527832031,
			"Absolute Acceleration Y" : -0.86930632591247559,
			"Absolute Acceleration Z" : 0.035908341407775879,
			"Absolute Velocity X" : 25.331527709960938,
			"Absolute Velocity Y" : 4.0349302291870117,
			"Absolute Velocity Z" : -0.37496492266654968,
			"ActorName" : "CAR 36",
			"BoundingBox3D Extent X" : 4.0999999046325684,
			"BoundingBox3D Extent Y" : 1.7466938495635986,
			"BoundingBox3D Extent Z" : 0.78176331520080566,
			"BoundingBox3D Orientation Quat W" : 0.99699854850769043,
			"BoundingBox3D Orientation Quat X" : 0.001768845715560019,
			"BoundingBox3D Orientation Quat Y" : 0.0073280590586364269,
			"BoundingBox3D Orientation Quat Z" : 0.077021829783916473,
			"BoundingBox3D Origin X" : -103.92472076416016,
			"BoundingBox3D Origin Y" : -7.7599802017211914,
			"BoundingBox3D Origin Z" : 1.4505523443222046,
			"ObjectId" : 36,
			"ObjectType" : "CAR",
			"Occluded" : 0.0,
			"Relative Acceleration X" : 0.39464366436004639,
			"Relative Acceleration Y" : 0.54782694578170776,
			"Relative Acceleration Z" : 0.29639387130737305,
			"Relative Velocity X" : -2.1772489547729492,
			"Relative Velocity Y" : -1.1367206573486328,
			"Relative Velocity Z" : 0.020322350785136223,
			"Truncated" : 0
		},
		{
			"Absolute Acceleration X" : 0.045904159545898438,
			"Absolute Acceleration Y" : -1.0550267696380615,
			"Absolute Acceleration Z" : 0.036503970623016357,
			"Absolute Velocity X" : 26.22907829284668,
			"Absolute Velocity Y" : 3.0802316665649414,
			"Absolute Velocity Z" : -0.35337820649147034,
			"ActorName" : "CAR 37",
			"BoundingBox3D Extent X" : 4.0999999046325684,
			"BoundingBox3D Extent Y" : 1.745970606803894,
			"BoundingBox3D Extent Z" : 0.81644999980926514,
			"BoundingBox3D Orientation Quat W" : 0.99829953908920288,
			"BoundingBox3D Orientation Quat X" : 0.0068919672630727291,
			"BoundingBox3D Orientation Quat Y" : 0.008084573782980442,
			"BoundingBox3D Orientation Quat Z" : 0.057257421314716339,
			"BoundingBox3D Origin X" : -75.767440795898438,
			"BoundingBox3D Origin Y" : -4.2332363128662109,
			"BoundingBox3D Origin Z" : 1.1219758987426758,
			"ObjectId" : 37,
			"ObjectType" : "CAR",
			"Occluded" : 0.0,
			"Relative Acceleration X" : -0.077117562294006348,
			"Relative Acceleration Y" : 0.36840790510177612,
			"Relative Acceleration Z" : 0.20955140888690948,
			"Relative Velocity X" : -1.4601807594299316,
			"Relative Velocity Y" : -0.65158355236053467,
			"Relative Velocity Z" : 0.0017672940157353878,
			"Truncated" : 0
		}
	],
	"FrameId" : 15926,
	"Timestamp" : 1676039893382046352,
	"TimestampMiddle" : 1676039893365046352
}