{
	"CapturedObjects" : 
	[
		{
			"Absolute Acceleration X" : -0.26617622375488281,
			"Absolute Acceleration Y" : -0.40186065435409546,
			"Absolute Acceleration Z" : -0.00046598911285400391,
			"Absolute Velocity X" : 16.593240737915039,
			"Absolute Velocity Y" : 0.87221860885620117,
			"Absolute Velocity Z" : -0.18016092479228973,
			"ActorName" : "CAR 00",
			"BoundingBox3D Extent X" : 4.235842227935791,
			"BoundingBox3D Extent Y" : 2.0896267890930176,
			"BoundingBox3D Extent Z" : 1.5755466222763062,
			"BoundingBox3D Orientation Quat W" : 0.99968802928924561,
			"BoundingBox3D Orientation Quat X" : 0.0029597950633615255,
			"BoundingBox3D Orientation Quat Y" : 0.0055457106791436672,
			"BoundingBox3D Orientation Quat Z" : 0.023343106731772423,
			"BoundingBox3D Origin X" : -18.042379379272461,
			"BoundingBox3D Origin Y" : 1.9832819700241089,
			"BoundingBox3D Origin Z" : 0.87782418727874756,
			"ObjectId" : 0,
			"ObjectType" : "CAR",
			"Occluded" : 0.0,
			"Relative Acceleration X" : -0.54575872421264648,
			"Relative Acceleration Y" : -0.32370340824127197,
			"Relative Acceleration Z" : 0.050079345703125,
			"Relative Velocity X" : 2.5156593322753906,
			"Relative Velocity Y" : 0.99219977855682373,
			"Relative Velocity Z" : -0.053606867790222168,
			"Truncated" : 0
		},
		{
			"Absolute Acceleration X" : -0.59676742553710938,
			"Absolute Acceleration Y" : 0.32437562942504883,
			"Absolute Acceleration Z" : -0.041916191577911377,
			"Absolute Velocity X" : 32.519210815429688,
			"Absolute Velocity Y" : -0.62752842903137207,
			"Absolute Velocity Z" : -0.26946592330932617,
			"ActorName" : "CAR 01",
			"BoundingBox3D Extent X" : 4.264348030090332,
			"BoundingBox3D Extent Y" : 1.8931920528411865,
			"BoundingBox3D Extent Z" : 1.3021485805511475,
			"BoundingBox3D Orientation Quat W" : -0.99984055757522583,
			"BoundingBox3D Orientation Quat X" : 0.0067610256373882294,
			"BoundingBox3D Orientation Quat Y" : -0.0048110615462064743,
			"BoundingBox3D Orientation Quat Z" : 0.011477765627205372,
			"BoundingBox3D Origin X" : 89.031471252441406,
			"BoundingBox3D Origin Y" : 18.812410354614258,
			"BoundingBox3D Origin Z" : -0.93803834915161133,
			"ObjectId" : 1,
			"ObjectType" : "CAR",
			"Occluded" : 0.0,
			"Relative Acceleration X" : -0.82710456848144531,
			"Relative Acceleration Y" : 0.15656179189682007,
			"Relative Acceleration Z" : 0.089210644364356995,
			"Relative Velocity X" : 18.41444206237793,
			"Relative Velocity Y" : -0.34517845511436462,
			"Relative Velocity Z" : -0.1030370220541954,
			"Truncated" : 0
		},
		{
			"Absolute Acceleration X" : -0.72623062133789062,
			"Absolute Acceleration Y" : 0.424396812915802,
			"Absolute Acceleration Z" : 0.0037135183811187744,
			"Absolute Velocity X" : 13.367938041687012,
			"Absolute Velocity Y" : -1.105754017829895,
			"Absolute Velocity Z" : -0.12773489952087402,
			"ActorName" : "CAR 03",
			"BoundingBox3D Extent X" : 4.3967618942260742,
			"BoundingBox3D Extent Y" : 1.8588123321533203,
			"BoundingBox3D Extent Z" : 1.4206863641738892,
			"BoundingBox3D Orientation Quat W" : -0.99904119968414307,
			"BoundingBox3D Orientation Quat X" : -0.00090974668273702264,
			"BoundingBox3D Orientation Quat Y" : -0.0046748947352170944,
			"BoundingBox3D Orientation Quat Z" : 0.043363973498344421,
			"BoundingBox3D Origin X" : -38.427555084228516,
			"BoundingBox3D Origin Y" : 0.50316840410232544,
			"BoundingBox3D Origin Z" : 0.99298679828643799,
			"ObjectId" : 3,
			"ObjectType" : "CAR",
			"Occluded" : 0.0,
			"Relative Acceleration X" : -1.0041768550872803,
			"Relative Acceleration Y" : 0.55113637447357178,
			"Relative Acceleration Z" : 0.066956266760826111,
			"Relative Velocity X" : -0.70872563123703003,
			"Relative Velocity Y" : -1.0173836946487427,
			"Relative Velocity Z" : -0.022224472835659981,
			"Truncated" : 0
		},
		{
			"Absolute Acceleration X" : -0.055974666029214859,
			"Absolute Acceleration Y" : 0.067661412060260773,
			"Absolute Acceleration Z" : 0.0066948053427040577,
			"Absolute Velocity X" : 12.53817081451416,
			"Absolute Velocity Y" : -0.80715525150299072,
			"Absolute Velocity Z" : -0.10474453121423721,
			"ActorName" : "CAR 05",
			"BoundingBox3D Extent X" : 4.2034134864807129,
			"BoundingBox3D Extent Y" : 1.8194049596786499,
			"BoundingBox3D Extent Z" : 1.486355185508728,
			"BoundingBox3D Orientation Quat W" : -0.99945253133773804,
			"BoundingBox3D Orientation Quat X" : -0.00061253109015524387,
			"BoundingBox3D Orientation Quat Y" : -0.0042086634784936905,
			"BoundingBox3D Orientation Quat Z" : 0.032638922333717346,
			"BoundingBox3D Origin X" : -55.618221282958984,
			"BoundingBox3D Origin Y" : 0.23773251473903656,
			"BoundingBox3D Origin Z" : 1.1965955495834351,
			"ObjectId" : 5,
			"ObjectType" : "CAR",
			"Occluded" : 0.0,
			"Relative Acceleration X" : -0.31800562143325806,
			"Relative Acceleration Y" : 0.063909664750099182,
			"Relative Acceleration Z" : -0.10666345059871674,
			"Relative Velocity X" : -1.5379120111465454,
			"Relative Velocity Y" : -0.74580502510070801,
			"Relative Velocity Z" : -0.011931771412491798,
			"Truncated" : 0
		},
		{
			"Absolute Acceleration X" : -1.0588102340698242,
			"Absolute Acceleration Y" : -0.072643697261810303,
			"Absolute Acceleration Z" : 0.016594663262367249,
			"Absolute Velocity X" : 15.47429084777832,
			"Absolute Velocity Y" : -0.30155777931213379,
			"Absolute Velocity Z" : -0.16422839462757111,
			"ActorName" : "CAR 06",
			"BoundingBox3D Extent X" : 4.2034726142883301,
			"BoundingBox3D Extent Y" : 2.0219583511352539,
			"BoundingBox3D Extent Z" : 1.5913317203521729,
			"BoundingBox3D Orientation Quat W" : -0.99983644485473633,
			"BoundingBox3D Orientation Quat X" : 0.0042141866870224476,
			"BoundingBox3D Orientation Quat Y" : -0.0051060831174254417,
			"BoundingBox3D Orientation Quat Z" : 0.016262464225292206,
			"BoundingBox3D Origin X" : 31.434579849243164,
			"BoundingBox3D Origin Y" : -1.656794548034668,
			"BoundingBox3D Origin Z" : 0.39754512906074524,
			"ObjectId" : 6,
			"ObjectType" : "CAR",
			"Occluded" : 0.0,
			"Relative Acceleration X" : -1.3457895517349243,
			"Relative Acceleration Y" : -0.12880542874336243,
			"Relative Acceleration Z" : 0.030760781839489937,
			"Relative Velocity X" : 1.4024144411087036,
			"Relative Velocity Y" : -0.10076647996902466,
			"Relative Velocity Z" : 0.011335647664964199,
			"Truncated" : 0
		},
		{
			"Absolute Acceleration X" : 0.10136985778808594,
			"Absolute Acceleration Y" : 0.17292144894599915,
			"Absolute Acceleration Z" : -0.010936126112937927,
			"Absolute Velocity X" : 19.434158325195312,
			"Absolute Velocity Y" : -0.26205065846443176,
			"Absolute Velocity Z" : -0.20824234187602997,
			"ActorName" : "CAR 07",
			"BoundingBox3D Extent X" : 4.0999999046325684,
			"BoundingBox3D Extent Y" : 1.5752513408660889,
			"BoundingBox3D Extent Z" : 1.6481819152832031,
			"BoundingBox3D Orientation Quat W" : -0.99974876642227173,
			"BoundingBox3D Orientation Quat X" : -0.013436947017908096,
			"BoundingBox3D Orientation Quat Y" : -0.004332598764449358,
			"BoundingBox3D Orientation Quat Z" : 0.013146359473466873,
			"BoundingBox3D Origin X" : 102.655029296875,
			"BoundingBox3D Origin Y" : 0.38647717237472534,
			"BoundingBox3D Origin Z" : -0.36064034700393677,
			"ObjectId" : 7,
			"ObjectType" : "CAR",
			"Occluded" : 0.0,
			"Relative Acceleration X" : -0.18015909194946289,
			"Relative Acceleration Y" : -0.066247455775737762,
			"Relative Acceleration Z" : -0.012765571475028992,
			"Relative Velocity X" : 5.3596410751342773,
			"Relative Velocity Y" : 0.052182372659444809,
			"Relative Velocity Z" : 0.024263482540845871,
			"Truncated" : 0
		},
		{
			"Absolute Acceleration X" : 0.078874588012695312,
			"Absolute Acceleration Y" : -0.0079038739204406738,
			"Absolute Acceleration Z" : -0.0030869767069816589,
			"Absolute Velocity X" : 22.736019134521484,
			"Absolute Velocity Y" : -0.41584888100624084,
			"Absolute Velocity Z" : -0.10990840196609497,
			"ActorName" : "CAR 08",
			"BoundingBox3D Extent X" : 5.7427949905395508,
			"BoundingBox3D Extent Y" : 2.4905531406402588,
			"BoundingBox3D Extent Z" : 1.9797494411468506,
			"BoundingBox3D Orientation Quat W" : -0.99952739477157593,
			"BoundingBox3D Orientation Quat X" : -0.025658534839749336,
			"BoundingBox3D Orientation Quat Y" : -0.0034881404135376215,
			"BoundingBox3D Orientation Quat Z" : 0.011494227685034275,
			"BoundingBox3D Origin X" : -16.326210021972656,
			"BoundingBox3D Origin Y" : 17.970746994018555,
			"BoundingBox3D Origin Z" : 0.67537152767181396,
			"ObjectId" : 8,
			"ObjectType" : "CAR",
			"Occluded" : 0.0,
			"Relative Acceleration X" : -0.15377616882324219,
			"Relative Acceleration Y" : 0.08068498969078064,
			"Relative Acceleration Z" : 0.14879962801933289,
			"Relative Velocity X" : 8.631342887878418,
			"Relative Velocity Y" : -0.29746019840240479,
			"Relative Velocity Z" : -0.029165796935558319,
			"Truncated" : 0
		},
		{
			"Absolute Acceleration X" : -0.068152867257595062,
			"Absolute Acceleration Y" : -0.13716240227222443,
			"Absolute Acceleration Z" : -0.096335157752037048,
			"Absolute Velocity X" : 32.715526580810547,
			"Absolute Velocity Y" : -0.94580185413360596,
			"Absolute Velocity Z" : -0.37880843877792358,
			"ActorName" : "CAR 11",
			"BoundingBox3D Extent X" : 4.0999999046325684,
			"BoundingBox3D Extent Y" : 1.6058875322341919,
			"BoundingBox3D Extent Z" : 1.3503061532974243,
			"BoundingBox3D Orientation Quat W" : -0.99977618455886841,
			"BoundingBox3D Orientation Quat X" : -0.013455106876790524,
			"BoundingBox3D Orientation Quat Y" : 0.0027383081614971161,
			"BoundingBox3D Orientation Quat Z" : 0.012994016520678997,
			"BoundingBox3D Origin X" : 112.95621490478516,
			"BoundingBox3D Origin Y" : 18.716997146606445,
			"BoundingBox3D Origin Z" : -1.2602537870407104,
			"ObjectId" : 11,
			"ObjectType" : "CAR",
			"Occluded" : 0.0,
			"Relative Acceleration X" : -0.33559790253639221,
			"Relative Acceleration Y" : 0.0090534621849656105,
			"Relative Acceleration Z" : 0.21715277433395386,
			"Relative Velocity X" : 18.611085891723633,
			"Relative Velocity Y" : -0.62379080057144165,
			"Relative Velocity Z" : -0.19147783517837524,
			"Truncated" : 0
		},
		{
			"Absolute Acceleration X" : -2.4887771606445312,
			"Absolute Acceleration Y" : -0.012709975242614746,
			"Absolute Acceleration Z" : -0.24761718511581421,
			"Absolute Velocity X" : 21.940370559692383,
			"Absolute Velocity Y" : -0.60065889358520508,
			"Absolute Velocity Z" : -0.16878841817378998,
			"ActorName" : "CAR 12",
			"BoundingBox3D Extent X" : 4.0999999046325684,
			"BoundingBox3D Extent Y" : 1.8191499710083008,
			"BoundingBox3D Extent Z" : 2.2632710933685303,
			"BoundingBox3D Orientation Quat W" : -0.99974864721298218,
			"BoundingBox3D Orientation Quat X" : -0.013046908192336559,
			"BoundingBox3D Orientation Quat Y" : 0.0081822387874126434,
			"BoundingBox3D Orientation Quat Z" : 0.014058118686079979,
			"BoundingBox3D Origin X" : 170.48187255859375,
			"BoundingBox3D Origin Y" : -1.6052868366241455,
			"BoundingBox3D Origin Z" : -0.28873088955879211,
			"ObjectId" : 12,
			"ObjectType" : "CAR",
			"Occluded" : 0.0,
			"Relative Acceleration X" : -2.7762627601623535,
			"Relative Acceleration Y" : -0.42432865500450134,
			"Relative Acceleration Z" : -0.28351625800132751,
			"Relative Velocity X" : 7.8690361976623535,
			"Relative Velocity Y" : -0.1784074455499649,
			"Relative Velocity Z" : 0.12550729513168335,
			"Truncated" : 0
		},
		{
			"Absolute Acceleration X" : -0.85201966762542725,
			"Absolute Acceleration Y" : -0.032524328678846359,
			"Absolute Acceleration Z" : -0.097789041697978973,
			"Absolute Velocity X" : 31.717601776123047,
			"Absolute Velocity Y" : -0.8334776759147644,
			"Absolute Velocity Z" : -0.27063408493995667,
			"ActorName" : "CAR 13",
			"BoundingBox3D Extent X" : 5.0383944511413574,
			"BoundingBox3D Extent Y" : 2.0900397300720215,
			"BoundingBox3D Extent Z" : 1.7203741073608398,
			"BoundingBox3D Orientation Quat W" : -0.99989950656890869,
			"BoundingBox3D Orientation Quat X" : 0.0011727359378710389,
			"BoundingBox3D Orientation Quat Y" : -0.0069780983030796051,
			"BoundingBox3D Orientation Quat Z" : 0.01166485995054245,
			"BoundingBox3D Origin X" : 15.733664512634277,
			"BoundingBox3D Origin Y" : 21.332080841064453,
			"BoundingBox3D Origin Z" : 0.30193498730659485,
			"ObjectId" : 13,
			"ObjectType" : "CAR",
			"Occluded" : 0.0,
			"Relative Acceleration X" : -1.1247953176498413,
			"Relative Acceleration Y" : 0.054742481559514999,
			"Relative Acceleration Z" : -0.040542390197515488,
			"Relative Velocity X" : 17.607444763183594,
			"Relative Velocity Y" : -0.6679835319519043,
			"Relative Velocity Z" : -0.17610256373882294,
			"Truncated" : 0
		},
		{
			"Absolute Acceleration X" : 0.775787353515625,
			"Absolute Acceleration Y" : -0.02097630500793457,
			"Absolute Acceleration Z" : -0.31354442238807678,
			"Absolute Velocity X" : 28.814468383789062,
			"Absolute Velocity Y" : -0.73608487844467163,
			"Absolute Velocity Z" : -0.57498782873153687,
			"ActorName" : "CAR 15",
			"BoundingBox3D Extent X" : 4.4445161819458008,
			"BoundingBox3D Extent Y" : 1.8999999761581421,
			"BoundingBox3D Extent Z" : 1.5254671573638916,
			"BoundingBox3D Orientation Quat W" : -0.99918901920318604,
			"BoundingBox3D Orientation Quat X" : 0.02980390377342701,
			"BoundingBox3D Orientation Quat Y" : 0.0025468901731073856,
			"BoundingBox3D Orientation Quat Z" : 0.0095571111887693405,
			"BoundingBox3D Origin X" : -47.612613677978516,
			"BoundingBox3D Origin Y" : 22.731494903564453,
			"BoundingBox3D Origin Z" : 0.68955594301223755,
			"ObjectId" : 15,
			"ObjectType" : "CAR",
			"Occluded" : 0.0,
			"Relative Acceleration X" : 0.55786895751953125,
			"Relative Acceleration Y" : 0.16431885957717896,
			"Relative Acceleration Z" : -0.10328671336174011,
			"Relative Velocity X" : 14.70133113861084,
			"Relative Velocity Y" : -0.67100852727890015,
			"Relative Velocity Z" : -0.53879272937774658,
			"Truncated" : 0
		},
		{
			"Absolute Acceleration X" : -0.30593022704124451,
			"Absolute Acceleration Y" : -0.22154876589775085,
			"Absolute Acceleration Z" : 0.016282076016068459,
			"Absolute Velocity X" : -0.27199235558509827,
			"Absolute Velocity Y" : 0.042642652988433838,
			"Absolute Velocity Z" : 0.021940983831882477,
			"ActorName" : "CAR 16",
			"BoundingBox3D Extent X" : 4.0999999046325684,
			"BoundingBox3D Extent Y" : 1.1051559448242188,
			"BoundingBox3D Extent Z" : 1.7776432037353516,
			"BoundingBox3D Orientation Quat W" : 0.99822938442230225,
			"BoundingBox3D Orientation Quat X" : 0.012780429795384407,
			"BoundingBox3D Orientation Quat Y" : 0.026959098875522614,
			"BoundingBox3D Orientation Quat Z" : -0.040684964507818222,
			"BoundingBox3D Origin X" : 88.138252258300781,
			"BoundingBox3D Origin Y" : -4.3167319297790527,
			"BoundingBox3D Origin Z" : -0.15185819566249847,
			"ObjectId" : 16,
			"ObjectType" : "CAR",
			"Occluded" : 0.0,
			"Relative Acceleration X" : -0.56407111883163452,
			"Relative Acceleration Y" : -0.16821981966495514,
			"Relative Acceleration Z" : 0.30333620309829712,
			"Relative Velocity X" : -14.338581085205078,
			"Relative Velocity Y" : 0.3446909487247467,
			"Relative Velocity Z" : 0.26583421230316162,
			"Truncated" : 0
		},
		{
			"Absolute Acceleration X" : 0.33452680706977844,
			"Absolute Acceleration Y" : -0.29919689893722534,
			"Absolute Acceleration Z" : -0.008847307413816452,
			"Absolute Velocity X" : 15.275043487548828,
			"Absolute Velocity Y" : -0.58356726169586182,
			"Absolute Velocity Z" : -0.15243156254291534,
			"ActorName" : "CAR 18",
			"BoundingBox3D Extent X" : 4.1225566864013672,
			"BoundingBox3D Extent Y" : 1.3198692798614502,
			"BoundingBox3D Extent Z" : 1.5615675449371338,
			"BoundingBox3D Orientation Quat W" : -0.99978309869766235,
			"BoundingBox3D Orientation Quat X" : 0.0057583972811698914,
			"BoundingBox3D Orientation Quat Y" : -0.004897155798971653,
			"BoundingBox3D Orientation Quat Z" : 0.019140247255563736,
			"BoundingBox3D Origin X" : 56.327663421630859,
			"BoundingBox3D Origin Y" : -1.931731104850769,
			"BoundingBox3D Origin Z" : 0.13235121965408325,
			"ObjectId" : 18,
			"ObjectType" : "CAR",
			"Occluded" : 0.0,
			"Relative Acceleration X" : 0.078477539122104645,
			"Relative Acceleration Y" : -0.20256775617599487,
			"Relative Acceleration Z" : 0.36113625764846802,
			"Relative Velocity X" : 1.2532262802124023,
			"Relative Velocity Y" : -0.28174582123756409,
			"Relative Velocity Z" : 0.21552398800849915,
			"Truncated" : 0
		},
		{
			"Absolute Acceleration X" : -1.7982425689697266,
			"Absolute Acceleration Y" : 0.19666102528572083,
			"Absolute Acceleration Z" : 0.15104448795318604,
			"Absolute Velocity X" : 24.095932006835938,
			"Absolute Velocity Y" : -0.50097227096557617,
			"Absolute Velocity Z" : -0.14516723155975342,
			"ActorName" : "CAR 19",
			"BoundingBox3D Extent X" : 4.0999999046325684,
			"BoundingBox3D Extent Y" : 1.5422316789627075,
			"BoundingBox3D Extent Z" : 1.8173509836196899,
			"BoundingBox3D Orientation Quat W" : -0.99963033199310303,
			"BoundingBox3D Orientation Quat X" : 0.014158124104142189,
			"BoundingBox3D Orientation Quat Y" : -0.00016860291361808777,
			"BoundingBox3D Orientation Quat Z" : 0.011002732440829277,
			"BoundingBox3D Origin X" : 121.60527038574219,
			"BoundingBox3D Origin Y" : 15.056567192077637,
			"BoundingBox3D Origin Z" : -1.0595865249633789,
			"ObjectId" : 19,
			"ObjectType" : "CAR",
			"Occluded" : 0.0,
			"Relative Acceleration X" : -2.039947509765625,
			"Relative Acceleration Y" : -0.078677743673324585,
			"Relative Acceleration Z" : 0.22009328007698059,
			"Relative Velocity X" : 9.9976930618286133,
			"Relative Velocity Y" : -0.1604195237159729,
			"Relative Velocity Z" : 0.065249525010585785,
			"Truncated" : 0
		},
		{
			"Absolute Acceleration X" : 0.17449566721916199,
			"Absolute Acceleration Y" : -1.7699140310287476,
			"Absolute Acceleration Z" : 0.16333441436290741,
			"Absolute Velocity X" : 9.9455785751342773,
			"Absolute Velocity Y" : -6.0753107070922852,
			"Absolute Velocity Z" : 0.076024003326892853,
			"ActorName" : "CAR 20",
			"BoundingBox3D Extent X" : 4.0999999046325684,
			"BoundingBox3D Extent Y" : 1.6025710105895996,
			"BoundingBox3D Extent Z" : 1.8528637886047363,
			"BoundingBox3D Orientation Quat W" : -0.96327686309814453,
			"BoundingBox3D Orientation Quat X" : -0.0083251940086483955,
			"BoundingBox3D Orientation Quat Y" : 0.0048856218345463276,
			"BoundingBox3D Orientation Quat Z" : 0.26826843619346619,
			"BoundingBox3D Origin X" : 98.378166198730469,
			"BoundingBox3D Origin Y" : -15.03870677947998,
			"BoundingBox3D Origin Z" : -0.1034502387046814,
			"ObjectId" : 20,
			"ObjectType" : "CAR",
			"Occluded" : 0.0,
			"Relative Acceleration X" : -0.066552430391311646,
			"Relative Acceleration Y" : -1.6881328821182251,
			"Relative Acceleration Z" : 0.4700150191783905,
			"Relative Velocity X" : -4.1071248054504395,
			"Relative Velocity Y" : -5.7626857757568359,
			"Relative Velocity Z" : 0.32438629865646362,
			"Truncated" : 0
		},
		{
			"Absolute Acceleration X" : -2.2069196701049805,
			"Absolute Acceleration Y" : -1.6460275650024414,
			"Absolute Acceleration Z" : 0.13211816549301147,
			"Absolute Velocity X" : 4.2891931533813477,
			"Absolute Velocity Y" : -12.257323265075684,
			"Absolute Velocity Z" : 0.65150582790374756,
			"ActorName" : "CAR 21",
			"BoundingBox3D Extent X" : 4.4318609237670898,
			"BoundingBox3D Extent Y" : 1.8999999761581421,
			"BoundingBox3D Extent Z" : 2.1494784355163574,
			"BoundingBox3D Orientation Quat W" : -0.81258022785186768,
			"BoundingBox3D Orientation Quat X" : -0.00058445188915356994,
			"BoundingBox3D Orientation Quat Y" : 0.031363360583782196,
			"BoundingBox3D Orientation Quat Z" : 0.58198702335357666,
			"BoundingBox3D Origin X" : 121.40035247802734,
			"BoundingBox3D Origin Y" : -44.800876617431641,
			"BoundingBox3D Origin Z" : 1.1821033954620361,
			"ObjectId" : 21,
			"ObjectType" : "CAR",
			"Occluded" : 0.0,
			"Relative Acceleration X" : -2.5885553359985352,
			"Relative Acceleration Y" : -1.9684810638427734,
			"Relative Acceleration Z" : -0.038562655448913574,
			"Relative Velocity X" : -9.7186698913574219,
			"Relative Velocity Y" : -11.903158187866211,
			"Relative Velocity Z" : 0.97094649076461792,
			"Truncated" : 0
		},
		{
			"Absolute Acceleration X" : 0.40777397155761719,
			"Absolute Acceleration Y" : -0.42625913023948669,
			"Absolute Acceleration Z" : 0.0097730159759521484,
			"Absolute Velocity X" : 31.756889343261719,
			"Absolute Velocity Y" : -0.70769047737121582,
			"Absolute Velocity Z" : -0.24969568848609924,
			"ActorName" : "CAR 22",
			"BoundingBox3D Extent X" : 4.0999999046325684,
			"BoundingBox3D Extent Y" : 1.7194300889968872,
			"BoundingBox3D Extent Z" : 1.6640387773513794,
			"BoundingBox3D Orientation Quat W" : -0.99988621473312378,
			"BoundingBox3D Orientation Quat X" : 0.0090586310252547264,
			"BoundingBox3D Orientation Quat Y" : -0.0032341079786419868,
			"BoundingBox3D Orientation Quat Z" : 0.010296916589140892,
			"BoundingBox3D Origin X" : 108.29012298583984,
			"BoundingBox3D Origin Y" : 19.922222137451172,
			"BoundingBox3D Origin Z" : -0.9357948899269104,
			"ObjectId" : 22,
			"ObjectType" : "CAR",
			"Occluded" : 0.0,
			"Relative Acceleration X" : 0.17923545837402344,
			"Relative Acceleration Y" : -0.650229811668396,
			"Relative Acceleration Z" : 0.13076099753379822,
			"Relative Velocity X" : 17.650426864624023,
			"Relative Velocity Y" : -0.39296907186508179,
			"Relative Velocity Z" : -0.068125173449516296,
			"Truncated" : 0
		},
		{
			"Absolute Acceleration X" : -0.1711597740650177,
			"Absolute Acceleration Y" : 0.028425468131899834,
			"Absolute Acceleration Z" : -0.29268065094947815,
			"Absolute Velocity X" : 27.891456604003906,
			"Absolute Velocity Y" : -0.17656885087490082,
			"Absolute Velocity Z" : -0.27032124996185303,
			"ActorName" : "CAR 23",
			"BoundingBox3D Extent X" : 4.1722078323364258,
			"BoundingBox3D Extent Y" : 1.7263823747634888,
			"BoundingBox3D Extent Z" : 1.1183193922042847,
			"BoundingBox3D Orientation Quat W" : 0.99999207258224487,
			"BoundingBox3D Orientation Quat X" : -0.0012207928812131286,
			"BoundingBox3D Orientation Quat Y" : 0.0011497959494590759,
			"BoundingBox3D Orientation Quat Z" : -0.0031421899329870939,
			"BoundingBox3D Origin X" : -24.305517196655273,
			"BoundingBox3D Origin Y" : 21.72490119934082,
			"BoundingBox3D Origin Z" : 0.2416730523109436,
			"ObjectId" : 23,
			"ObjectType" : "CAR",
			"Occluded" : 0.0,
			"Relative Acceleration X" : -0.4572741687297821,
			"Relative Acceleration Y" : 0.08135010302066803,
			"Relative Acceleration Z" : -0.3282184898853302,
			"Relative Velocity X" : 13.78093433380127,
			"Relative Velocity Y" : -0.074624814093112946,
			"Relative Velocity Z" : -0.2078825831413269,
			"Truncated" : 0
		},
		{
			"Absolute Acceleration X" : -2.2985594272613525,
			"Absolute Acceleration Y" : -0.0949273481965065,
			"Absolute Acceleration Z" : 0.070744208991527557,
			"Absolute Velocity X" : 0.61129480600357056,
			"Absolute Velocity Y" : -11.543253898620605,
			"Absolute Velocity Z" : 0.74871563911437988,
			"ActorName" : "CAR 24",
			"BoundingBox3D Extent X" : 3.8559150695800781,
			"BoundingBox3D Extent Y" : 1.8999999761581421,
			"BoundingBox3D Extent Z" : 1.7364833354949951,
			"BoundingBox3D Orientation Quat W" : -0.72337895631790161,
			"BoundingBox3D Orientation Quat X" : 0.0052151116542518139,
			"BoundingBox3D Orientation Quat Y" : 0.038895945996046066,
			"BoundingBox3D Orientation Quat Z" : 0.68932271003723145,
			"BoundingBox3D Origin X" : 124.76410675048828,
			"BoundingBox3D Origin Y" : -62.5277099609375,
			"BoundingBox3D Origin Z" : 1.998173713684082,
			"ObjectId" : 24,
			"ObjectType" : "CAR",
			"Occluded" : 0.0,
			"Relative Acceleration X" : -0.78002536296844482,
			"Relative Acceleration Y" : 2.1963539123535156,
			"Relative Acceleration Z" : -0.9516373872756958,
			"Relative Velocity X" : -13.367639541625977,
			"Relative Velocity Y" : -11.179947853088379,
			"Relative Velocity Z" : 1.1185377836227417,
			"Truncated" : 0
		},
		{
			"Absolute Acceleration X" : -0.28131386637687683,
			"Absolute Acceleration Y" : 0.28193849325180054,
			"Absolute Acceleration Z" : 0.045539908111095428,
			"Absolute Velocity X" : 16.790533065795898,
			"Absolute Velocity Y" : -0.40312844514846802,
			"Absolute Velocity Z" : -0.0481610968708992,
			"ActorName" : "CAR 25",
			"BoundingBox3D Extent X" : 4.0999999046325684,
			"BoundingBox3D Extent Y" : 1.5444560050964355,
			"BoundingBox3D Extent Z" : 0.85963785648345947,
			"BoundingBox3D Orientation Quat W" : -0.99998140335083008,
			"BoundingBox3D Orientation Quat X" : -0.0016943785594776273,
			"BoundingBox3D Orientation Quat Y" : 0.00033740766230039299,
			"BoundingBox3D Orientation Quat Z" : 0.0054072379134595394,
			"BoundingBox3D Origin X" : -117.5997314453125,
			"BoundingBox3D Origin Y" : 5.1012959480285645,
			"BoundingBox3D Origin Z" : 1.173763632774353,
			"ObjectId" : 25,
			"ObjectType" : "CAR",
			"Occluded" : 0.0,
			"Relative Acceleration X" : -0.54204261302947998,
			"Relative Acceleration Y" : 0.8660321831703186,
			"Relative Acceleration Z" : 2.4475295543670654,
			"Relative Velocity X" : 2.7064895629882812,
			"Relative Velocity Y" : -0.44710031151771545,
			"Relative Velocity Z" : -0.024101845920085907,
			"Truncated" : 0
		}
	],
	"FrameId" : 19702,
	"Timestamp" : 1676040145115418448,
	"TimestampMiddle" : 1676040145098418448
}