{
	"CapturedObjects" : 
	[
		{
			"Absolute Acceleration X" : -0.19977760314941406,
			"Absolute Acceleration Y" : 0.085198104381561279,
			"Absolute Acceleration Z" : 0.49643546342849731,
			"Absolute Velocity X" : 21.926599502563477,
			"Absolute Velocity Y" : -0.4083937406539917,
			"Absolute Velocity Z" : -0.75322419404983521,
			"ActorName" : "CAR 08",
			"BoundingBox3D Extent X" : 4.2699203491210938,
			"BoundingBox3D Extent Y" : 2.0144033432006836,
			"BoundingBox3D Extent Z" : 1.6600271463394165,
			"BoundingBox3D Orientation Quat W" : -0.99980294704437256,
			"BoundingBox3D Orientation Quat X" : -0.0046649351716041565,
			"BoundingBox3D Orientation Quat Y" : -0.016994625329971313,
			"BoundingBox3D Orientation Quat Z" : 0.0077545875683426857,
			"BoundingBox3D Origin X" : -30.197113037109375,
			"BoundingBox3D Origin Y" : 0.66693657636642456,
			"BoundingBox3D Origin Z" : 1.3807468414306641,
			"ObjectId" : 8,
			"ObjectType" : "CAR",
			"Occluded" : 0.0,
			"Relative Acceleration X" : -0.24005794525146484,
			"Relative Acceleration Y" : -0.10424017906188965,
			"Relative Acceleration Z" : -0.012462019920349121,
			"Relative Velocity X" : 1.1362686157226562,
			"Relative Velocity Y" : -0.054339956492185593,
			"Relative Velocity Z" : -0.37041091918945312,
			"Truncated" : 0
		},
		{
			"Absolute Acceleration X" : 0.17243766784667969,
			"Absolute Acceleration Y" : -0.3436911404132843,
			"Absolute Acceleration Z" : 0.15399092435836792,
			"Absolute Velocity X" : 17.107690811157227,
			"Absolute Velocity Y" : -0.17159371078014374,
			"Absolute Velocity Z" : -0.33227869868278503,
			"ActorName" : "CAR 10",
			"BoundingBox3D Extent X" : 5.4278655052185059,
			"BoundingBox3D Extent Y" : 2.6808505058288574,
			"BoundingBox3D Extent Z" : 1.8241925239562988,
			"BoundingBox3D Orientation Quat W" : 0.99987608194351196,
			"BoundingBox3D Orientation Quat X" : -0.0086503317579627037,
			"BoundingBox3D Orientation Quat Y" : 0.0098923640325665474,
			"BoundingBox3D Orientation Quat Z" : -0.0065453373827040195,
			"BoundingBox3D Origin X" : -14.623226165771484,
			"BoundingBox3D Origin Y" : -2.4324040412902832,
			"BoundingBox3D Origin Z" : 1.1418410539627075,
			"ObjectId" : 10,
			"ObjectType" : "CAR",
			"Occluded" : 0.0,
			"Relative Acceleration X" : 0.14891791343688965,
			"Relative Acceleration Y" : -0.44448590278625488,
			"Relative Acceleration Z" : -0.11145264655351639,
			"Relative Velocity X" : -3.7008967399597168,
			"Relative Velocity Y" : 0.101229228079319,
			"Relative Velocity Z" : -0.028276296332478523,
			"Truncated" : 0
		},
		{
			"Absolute Acceleration X" : -0.63560295104980469,
			"Absolute Acceleration Y" : -0.22289878129959106,
			"Absolute Acceleration Z" : 0.46218103170394897,
			"Absolute Velocity X" : 20.195951461791992,
			"Absolute Velocity Y" : -0.46025282144546509,
			"Absolute Velocity Z" : -0.77252840995788574,
			"ActorName" : "CAR 12",
			"BoundingBox3D Extent X" : 4.3477344512939453,
			"BoundingBox3D Extent Y" : 2.0270838737487793,
			"BoundingBox3D Extent Z" : 1.5336672067642212,
			"BoundingBox3D Orientation Quat W" : -0.99968510866165161,
			"BoundingBox3D Orientation Quat X" : 0.010398127138614655,
			"BoundingBox3D Orientation Quat Y" : -0.018948983401060104,
			"BoundingBox3D Orientation Quat Z" : 0.011433814652264118,
			"BoundingBox3D Origin X" : -36.856536865234375,
			"BoundingBox3D Origin Y" : -2.05999755859375,
			"BoundingBox3D Origin Z" : 1.5512046813964844,
			"ObjectId" : 12,
			"ObjectType" : "CAR",
			"Occluded" : 0.0,
			"Relative Acceleration X" : -0.67548179626464844,
			"Relative Acceleration Y" : -0.39356398582458496,
			"Relative Acceleration Z" : -0.13794788718223572,
			"Relative Velocity X" : -0.60832035541534424,
			"Relative Velocity Y" : -0.07340557873249054,
			"Relative Velocity Z" : -0.40555799007415771,
			"Truncated" : 0
		},
		{
			"Absolute Acceleration X" : 0.15786075592041016,
			"Absolute Acceleration Y" : 0.08208310604095459,
			"Absolute Acceleration Z" : 0.10429032146930695,
			"Absolute Velocity X" : 13.946352005004883,
			"Absolute Velocity Y" : -0.18271100521087646,
			"Absolute Velocity Z" : -0.22791266441345215,
			"ActorName" : "CAR 76",
			"BoundingBox3D Extent X" : 4.2790994644165039,
			"BoundingBox3D Extent Y" : 2.1297554969787598,
			"BoundingBox3D Extent Z" : 1.5282770395278931,
			"BoundingBox3D Orientation Quat W" : -0.99986326694488525,
			"BoundingBox3D Orientation Quat X" : -0.0086314128711819649,
			"BoundingBox3D Orientation Quat Y" : -0.0087468335404992104,
			"BoundingBox3D Orientation Quat Z" : 0.0080441748723387718,
			"BoundingBox3D Origin X" : -7.0524101257324219,
			"BoundingBox3D Origin Y" : -5.720365047454834,
			"BoundingBox3D Origin Z" : 0.83826464414596558,
			"ObjectId" : 76,
			"ObjectType" : "CAR",
			"Occluded" : 0.0,
			"Relative Acceleration X" : 0.14091968536376953,
			"Relative Acceleration Y" : 0.038149945437908173,
			"Relative Acceleration Z" : -0.049735568463802338,
			"Relative Velocity X" : -6.8797144889831543,
			"Relative Velocity Y" : 0.052186325192451477,
			"Relative Velocity Z" : 0.019798394292593002,
			"Truncated" : 0
		},
		{
			"Absolute Acceleration X" : 1.0757020711898804,
			"Absolute Acceleration Y" : 0.13075453042984009,
			"Absolute Acceleration Z" : -0.019101999700069427,
			"Absolute Velocity X" : -1.2989485263824463,
			"Absolute Velocity Y" : 0.054416205734014511,
			"Absolute Velocity Z" : 0.11217332631349564,
			"ActorName" : "CAR 115",
			"BoundingBox3D Extent X" : 4.3207364082336426,
			"BoundingBox3D Extent Y" : 2.3077139854431152,
			"BoundingBox3D Extent Z" : 1.6247607469558716,
			"BoundingBox3D Orientation Quat W" : 0.014365846291184425,
			"BoundingBox3D Orientation Quat X" : -0.0029145055450499058,
			"BoundingBox3D Orientation Quat Y" : 0.042325969785451889,
			"BoundingBox3D Orientation Quat Z" : 0.99878770112991333,
			"BoundingBox3D Origin X" : -37.50274658203125,
			"BoundingBox3D Origin Y" : 20.892631530761719,
			"BoundingBox3D Origin Z" : 1.7359790802001953,
			"ObjectId" : 115,
			"ObjectType" : "CAR",
			"Occluded" : 0.0,
			"Relative Acceleration X" : 1.0427875518798828,
			"Relative Acceleration Y" : 0.27074900269508362,
			"Relative Acceleration Z" : 0.29174071550369263,
			"Relative Velocity X" : -21.987600326538086,
			"Relative Velocity Y" : 0.43029922246932983,
			"Relative Velocity Z" : 0.61014097929000854,
			"Truncated" : 0
		},
		{
			"Absolute Acceleration X" : 0.031411528587341309,
			"Absolute Acceleration Y" : -0.0024807860609143972,
			"Absolute Acceleration Z" : -0.14339205622673035,
			"Absolute Velocity X" : -0.86867403984069824,
			"Absolute Velocity Y" : -0.0078671937808394432,
			"Absolute Velocity Z" : -0.067123554646968842,
			"ActorName" : "CAR 116",
			"BoundingBox3D Extent X" : 4.8723711967468262,
			"BoundingBox3D Extent Y" : 1.8999999761581421,
			"BoundingBox3D Extent Z" : 1.1943989992141724,
			"BoundingBox3D Orientation Quat W" : 0.011583490297198296,
			"BoundingBox3D Orientation Quat X" : 0.015546745620667934,
			"BoundingBox3D Orientation Quat Y" : 0.032056890428066254,
			"BoundingBox3D Orientation Quat Z" : 0.99875760078430176,
			"BoundingBox3D Origin X" : -47.077793121337891,
			"BoundingBox3D Origin Y" : 20.592889785766602,
			"BoundingBox3D Origin Z" : 1.9112249612808228,
			"ObjectId" : 116,
			"ObjectType" : "CAR",
			"Occluded" : 0.0,
			"Relative Acceleration X" : 0.044567804783582687,
			"Relative Acceleration Y" : 0.10566858947277069,
			"Relative Acceleration Z" : -0.17534016072750092,
			"Relative Velocity X" : -21.528013229370117,
			"Relative Velocity Y" : 0.44154304265975952,
			"Relative Velocity Z" : 0.69820761680603027,
			"Truncated" : 0
		},
		{
			"Absolute Acceleration X" : 1.3096399307250977,
			"Absolute Acceleration Y" : -0.01880621537566185,
			"Absolute Acceleration Z" : -0.094375737011432648,
			"Absolute Velocity X" : -0.0090670352801680565,
			"Absolute Velocity Y" : -0.040294181555509567,
			"Absolute Velocity Z" : -0.070242851972579956,
			"ActorName" : "CAR 117",
			"BoundingBox3D Extent X" : 2.9113047122955322,
			"BoundingBox3D Extent Y" : 1.8999999761581421,
			"BoundingBox3D Extent Z" : 0.62377727031707764,
			"BoundingBox3D Orientation Quat W" : -0.010455472394824028,
			"BoundingBox3D Orientation Quat X" : 0.033640440553426743,
			"BoundingBox3D Orientation Quat Y" : -0.023198854178190231,
			"BoundingBox3D Orientation Quat Z" : 0.99741244316101074,
			"BoundingBox3D Origin X" : -31.287639617919922,
			"BoundingBox3D Origin Y" : 23.642459869384766,
			"BoundingBox3D Origin Z" : 1.2924591302871704,
			"ObjectId" : 117,
			"ObjectType" : "CAR",
			"Occluded" : 0.0,
			"Relative Acceleration X" : 1.2920807600021362,
			"Relative Acceleration Y" : 0.060307968407869339,
			"Relative Acceleration Z" : -0.044298570603132248,
			"Relative Velocity X" : -20.684144973754883,
			"Relative Velocity Y" : 0.30910363793373108,
			"Relative Velocity Z" : 0.44228467345237732,
			"Truncated" : 0
		},
		{
			"Absolute Acceleration X" : -0.51613616943359375,
			"Absolute Acceleration Y" : 0.19046545028686523,
			"Absolute Acceleration Z" : -0.24478578567504883,
			"Absolute Velocity X" : 17.559381484985352,
			"Absolute Velocity Y" : 0.73127436637878418,
			"Absolute Velocity Z" : -0.8875734806060791,
			"ActorName" : "CAR 123",
			"BoundingBox3D Extent X" : 4.1979241371154785,
			"BoundingBox3D Extent Y" : 2.1736588478088379,
			"BoundingBox3D Extent Z" : 1.3563997745513916,
			"BoundingBox3D Orientation Quat W" : 0.99952435493469238,
			"BoundingBox3D Orientation Quat X" : -0.001250558765605092,
			"BoundingBox3D Orientation Quat Y" : 0.0256517194211483,
			"BoundingBox3D Orientation Quat Z" : 0.016457900404930115,
			"BoundingBox3D Origin X" : 91.076087951660156,
			"BoundingBox3D Origin Y" : 1.3130530118942261,
			"BoundingBox3D Origin Z" : -1.4779790639877319,
			"ObjectId" : 123,
			"ObjectType" : "CAR",
			"Occluded" : 0.0,
			"Relative Acceleration X" : -0.53348076343536377,
			"Relative Acceleration Y" : 0.17491632699966431,
			"Relative Acceleration Z" : 0.7782433032989502,
			"Relative Velocity X" : -3.2326672077178955,
			"Relative Velocity Y" : 0.48376765847206116,
			"Relative Velocity Z" : -0.77991312742233276,
			"Truncated" : 0
		},
		{
			"Absolute Acceleration X" : -0.26620101928710938,
			"Absolute Acceleration Y" : 0.055083870887756348,
			"Absolute Acceleration Z" : -0.24002218246459961,
			"Absolute Velocity X" : 18.165857315063477,
			"Absolute Velocity Y" : 0.72432935237884521,
			"Absolute Velocity Z" : -0.98105132579803467,
			"ActorName" : "CAR 124",
			"BoundingBox3D Extent X" : 4.0999999046325684,
			"BoundingBox3D Extent Y" : 1.8231289386749268,
			"BoundingBox3D Extent Z" : 1.790833592414856,
			"BoundingBox3D Orientation Quat W" : 0.99939006567001343,
			"BoundingBox3D Orientation Quat X" : 0.00056640029652044177,
			"BoundingBox3D Orientation Quat Y" : 0.026813389733433723,
			"BoundingBox3D Orientation Quat Z" : 0.019933948293328285,
			"BoundingBox3D Origin X" : 94.959884643554688,
			"BoundingBox3D Origin Y" : -3.9633662700653076,
			"BoundingBox3D Origin Z" : -1.4435924291610718,
			"ObjectId" : 124,
			"ObjectType" : "CAR",
			"Occluded" : 0.0,
			"Relative Acceleration X" : -0.28313064575195312,
			"Relative Acceleration Y" : 0.045514717698097229,
			"Relative Acceleration Z" : 0.74379777908325195,
			"Relative Velocity X" : -2.6529507637023926,
			"Relative Velocity Y" : 0.45790550112724304,
			"Relative Velocity Z" : -0.92632293701171875,
			"Truncated" : 0
		},
		{
			"Absolute Acceleration X" : 0.61717504262924194,
			"Absolute Acceleration Y" : -0.0026395656168460846,
			"Absolute Acceleration Z" : -0.060188829898834229,
			"Absolute Velocity X" : 0.85493314266204834,
			"Absolute Velocity Y" : 0.13219068944454193,
			"Absolute Velocity Z" : -0.075983859598636627,
			"ActorName" : "CAR 125",
			"BoundingBox3D Extent X" : 4.8496842384338379,
			"BoundingBox3D Extent Y" : 1.8892860412597656,
			"BoundingBox3D Extent Z" : 1.9452694654464722,
			"BoundingBox3D Orientation Quat W" : -0.013880455866456032,
			"BoundingBox3D Orientation Quat X" : 0.039489865303039551,
			"BoundingBox3D Orientation Quat Y" : -0.0020388215780258179,
			"BoundingBox3D Orientation Quat Z" : 0.99880224466323853,
			"BoundingBox3D Origin X" : -53.780284881591797,
			"BoundingBox3D Origin Y" : 23.029661178588867,
			"BoundingBox3D Origin Z" : 2.6663618087768555,
			"ObjectId" : 125,
			"ObjectType" : "CAR",
			"Occluded" : 0.0,
			"Relative Acceleration X" : 0.57253074645996094,
			"Relative Acceleration Y" : 0.080318927764892578,
			"Relative Acceleration Z" : 0.039740800857543945,
			"Relative Velocity X" : -19.820352554321289,
			"Relative Velocity Y" : 0.58559286594390869,
			"Relative Velocity Z" : 0.4846329391002655,
			"Truncated" : 0
		},
		{
			"Absolute Acceleration X" : -1.7976639270782471,
			"Absolute Acceleration Y" : -0.79468786716461182,
			"Absolute Acceleration Z" : 0.14045098423957825,
			"Absolute Velocity X" : -2.9323303699493408,
			"Absolute Velocity Y" : 0.023560831323266029,
			"Absolute Velocity Z" : 0.22054001688957214,
			"ActorName" : "CAR 126",
			"BoundingBox3D Extent X" : 4.7677597999572754,
			"BoundingBox3D Extent Y" : 1.75486159324646,
			"BoundingBox3D Extent Z" : 1.265733003616333,
			"BoundingBox3D Orientation Quat W" : -0.013008427806198597,
			"BoundingBox3D Orientation Quat X" : 0.03587520495057106,
			"BoundingBox3D Orientation Quat Y" : -0.0058382130227982998,
			"BoundingBox3D Orientation Quat Z" : 0.99923974275588989,
			"BoundingBox3D Origin X" : -55.8505859375,
			"BoundingBox3D Origin Y" : 20.417871475219727,
			"BoundingBox3D Origin Z" : 2.4285764694213867,
			"ObjectId" : 126,
			"ObjectType" : "CAR",
			"Occluded" : 0.0,
			"Relative Acceleration X" : -1.8377914428710938,
			"Relative Acceleration Y" : -0.65978223085403442,
			"Relative Acceleration Z" : 0.23190009593963623,
			"Relative Velocity X" : -23.622695922851562,
			"Relative Velocity Y" : 0.48899951577186584,
			"Relative Velocity Z" : 0.74959421157836914,
			"Truncated" : 0
		},
		{
			"Absolute Acceleration X" : -0.073637008666992188,
			"Absolute Acceleration Y" : 0.028217300772666931,
			"Absolute Acceleration Z" : -0.33086064457893372,
			"Absolute Velocity X" : -21.94287109375,
			"Absolute Velocity Y" : -0.47253301739692688,
			"Absolute Velocity Z" : 0.61105829477310181,
			"ActorName" : "CAR 127",
			"BoundingBox3D Extent X" : 4.2537407875061035,
			"BoundingBox3D Extent Y" : 1.6770579814910889,
			"BoundingBox3D Extent Z" : 1.4993448257446289,
			"BoundingBox3D Orientation Quat W" : -0.0085682682693004608,
			"BoundingBox3D Orientation Quat X" : 0.013894917443394661,
			"BoundingBox3D Orientation Quat Y" : -0.0017137170070782304,
			"BoundingBox3D Orientation Quat Z" : 0.99985021352767944,
			"BoundingBox3D Origin X" : 57.217952728271484,
			"BoundingBox3D Origin Y" : 6.0708184242248535,
			"BoundingBox3D Origin Z" : -0.095282770693302155,
			"ObjectId" : 127,
			"ObjectType" : "CAR",
			"Occluded" : 0.0,
			"Relative Acceleration X" : -0.0873260498046875,
			"Relative Acceleration Y" : 0.55559694766998291,
			"Relative Acceleration Z" : 1.3253719806671143,
			"Relative Velocity X" : -42.711936950683594,
			"Relative Velocity Y" : -0.57837128639221191,
			"Relative Velocity Z" : 0.6953083872795105,
			"Truncated" : 0
		},
		{
			"Absolute Acceleration X" : 0.18423406779766083,
			"Absolute Acceleration Y" : 0.036792747676372528,
			"Absolute Acceleration Z" : 0.11680764704942703,
			"Absolute Velocity X" : 0.21327534317970276,
			"Absolute Velocity Y" : 0.139910489320755,
			"Absolute Velocity Z" : 0.045055486261844635,
			"ActorName" : "CAR 128",
			"BoundingBox3D Extent X" : 4.1203689575195312,
			"BoundingBox3D Extent Y" : 2.6228203773498535,
			"BoundingBox3D Extent Z" : 1.2528584003448486,
			"BoundingBox3D Orientation Quat W" : -0.66717618703842163,
			"BoundingBox3D Orientation Quat X" : -0.040538385510444641,
			"BoundingBox3D Orientation Quat Y" : -0.0056621851399540901,
			"BoundingBox3D Orientation Quat Z" : -0.74377447366714478,
			"BoundingBox3D Origin X" : -35.2008056640625,
			"BoundingBox3D Origin Y" : 24.923578262329102,
			"BoundingBox3D Origin Z" : 1.542111873626709,
			"ObjectId" : 128,
			"ObjectType" : "CAR",
			"Occluded" : 0.0,
			"Relative Acceleration X" : 0.18240667879581451,
			"Relative Acceleration Y" : 0.17321372032165527,
			"Relative Acceleration Z" : -0.75034999847412109,
			"Relative Velocity X" : -20.456232070922852,
			"Relative Velocity Y" : 0.50892758369445801,
			"Relative Velocity Z" : 0.57782208919525146,
			"Truncated" : 0
		},
		{
			"Absolute Acceleration X" : 0.89454585313796997,
			"Absolute Acceleration Y" : 4.0560803413391113,
			"Absolute Acceleration Z" : -0.027595488354563713,
			"Absolute Velocity X" : 0.11976155638694763,
			"Absolute Velocity Y" : -1.6962684392929077,
			"Absolute Velocity Z" : -0.14308321475982666,
			"ActorName" : "PEDESTRIAN 129",
			"BoundingBox3D Extent X" : 0.84475076198577881,
			"BoundingBox3D Extent Y" : 0.49931758642196655,
			"BoundingBox3D Extent Z" : 0.91624176502227783,
			"BoundingBox3D Orientation Quat W" : -0.7252047061920166,
			"BoundingBox3D Orientation Quat X" : -0.0045955847017467022,
			"BoundingBox3D Orientation Quat Y" : -0.051666390150785446,
			"BoundingBox3D Orientation Quat Z" : 0.68645983934402466,
			"BoundingBox3D Origin X" : -30.951889038085938,
			"BoundingBox3D Origin Y" : 30.725225448608398,
			"BoundingBox3D Origin Z" : 2.0813968181610107,
			"ObjectId" : 129,
			"ObjectType" : "PEDESTRIAN",
			"Occluded" : 0.0,
			"Relative Acceleration X" : 0.79060459136962891,
			"Relative Acceleration Y" : 4.1291022300720215,
			"Relative Acceleration Z" : -0.036032110452651978,
			"Relative Velocity X" : -20.513193130493164,
			"Relative Velocity Y" : -1.3500510454177856,
			"Relative Velocity Z" : 0.31922459602355957,
			"Truncated" : 0
		},
		{
			"Absolute Acceleration X" : -0.3933718204498291,
			"Absolute Acceleration Y" : -0.72625148296356201,
			"Absolute Acceleration Z" : 0.006405949592590332,
			"Absolute Velocity X" : -3.7808003425598145,
			"Absolute Velocity Y" : -0.6763119101524353,
			"Absolute Velocity Z" : 0.25760313868522644,
			"ActorName" : "CAR 130",
			"BoundingBox3D Extent X" : 4.386289119720459,
			"BoundingBox3D Extent Y" : 1.7516076564788818,
			"BoundingBox3D Extent Z" : 1.0120282173156738,
			"BoundingBox3D Orientation Quat W" : -0.096765391528606415,
			"BoundingBox3D Orientation Quat X" : 0.034695174545049667,
			"BoundingBox3D Orientation Quat Y" : -0.0090470938012003899,
			"BoundingBox3D Orientation Quat Z" : 0.99465018510818481,
			"BoundingBox3D Origin X" : -65.567779541015625,
			"BoundingBox3D Origin Y" : 20.196455001831055,
			"BoundingBox3D Origin Z" : 2.9833292961120605,
			"ObjectId" : 130,
			"ObjectType" : "CAR",
			"Occluded" : 0.0,
			"Relative Acceleration X" : -0.44131851196289062,
			"Relative Acceleration Y" : -0.59752762317657471,
			"Relative Acceleration Z" : 0.00058460235595703125,
			"Relative Velocity X" : -24.471145629882812,
			"Relative Velocity Y" : -0.16695655882358551,
			"Relative Velocity Z" : 0.80084842443466187,
			"Truncated" : 0
		}
	],
	"FrameId" : 33511,
	"Timestamp" : 1676041065715391192,
	"TimestampMiddle" : 1676041065698391192
}