{
	"CapturedObjects" : 
	[
		{
			"Absolute Acceleration X" : -0.014136306010186672,
			"Absolute Acceleration Y" : -0.0011089483741670847,
			"Absolute Acceleration Z" : -0.0012009807396680117,
			"Absolute Velocity X" : 0.0079535897821187973,
			"Absolute Velocity Y" : 0.0021739741787314415,
			"Absolute Velocity Z" : 6.7142259467800613e-06,
			"ActorName" : "CAR 01",
			"BoundingBox3D Extent X" : 4.3846368789672852,
			"BoundingBox3D Extent Y" : 2.3503270149230957,
			"BoundingBox3D Extent Z" : 1.4755876064300537,
			"BoundingBox3D Orientation Quat W" : 0.99913305044174194,
			"BoundingBox3D Orientation Quat X" : 0.0043039075098931789,
			"BoundingBox3D Orientation Quat Y" : 0.0038508649449795485,
			"BoundingBox3D Orientation Quat Z" : -0.041001368314027786,
			"BoundingBox3D Origin X" : 13.949724197387695,
			"BoundingBox3D Origin Y" : -3.1320886611938477,
			"BoundingBox3D Origin Z" : 0.64729726314544678,
			"ObjectId" : 1,
			"ObjectType" : "CAR",
			"Occluded" : 0.0,
			"Relative Acceleration X" : 0.002597299637272954,
			"Relative Acceleration Y" : -0.0018005360616371036,
			"Relative Acceleration Z" : -0.00037770241033285856,
			"Relative Velocity X" : 0.0012133028358221054,
			"Relative Velocity Y" : 0.0027757377829402685,
			"Relative Velocity Z" : -0.00035637829569168389,
			"Truncated" : 0
		},
		{
			"Absolute Acceleration X" : -0.0011066198348999023,
			"Absolute Acceleration Y" : 0.022212300449609756,
			"Absolute Acceleration Z" : 0.0023777550086379051,
			"Absolute Velocity X" : 1.0433944463729858,
			"Absolute Velocity Y" : -0.0088399024680256844,
			"Absolute Velocity Z" : -0.0055524660274386406,
			"ActorName" : "CAR 03",
			"BoundingBox3D Extent X" : 4.3525314331054688,
			"BoundingBox3D Extent Y" : 1.848330020904541,
			"BoundingBox3D Extent Z" : 1.6735094785690308,
			"BoundingBox3D Orientation Quat W" : 0.99978899955749512,
			"BoundingBox3D Orientation Quat X" : -0.018422849476337433,
			"BoundingBox3D Orientation Quat Y" : 0.0022262812126427889,
			"BoundingBox3D Orientation Quat Z" : -0.0080607356503605843,
			"BoundingBox3D Origin X" : -14.699172019958496,
			"BoundingBox3D Origin Y" : 0.37705078721046448,
			"BoundingBox3D Origin Z" : 0.87376171350479126,
			"ObjectId" : 3,
			"ObjectType" : "CAR",
			"Occluded" : 0.0,
			"Relative Acceleration X" : 0.015375733375549316,
			"Relative Acceleration Y" : 0.019283726811408997,
			"Relative Acceleration Z" : 0.0052641099318861961,
			"Relative Velocity X" : 1.0367742776870728,
			"Relative Velocity Y" : -0.0071488646790385246,
			"Relative Velocity Z" : -0.0073091946542263031,
			"Truncated" : 0
		},
		{
			"Absolute Acceleration X" : -0.0089590791612863541,
			"Absolute Acceleration Y" : 0.00035414844751358032,
			"Absolute Acceleration Z" : -0.00010814153938554227,
			"Absolute Velocity X" : 0.0072226459160447121,
			"Absolute Velocity Y" : 0.0017362512880936265,
			"Absolute Velocity Z" : -0.00097029772587120533,
			"ActorName" : "CAR 04",
			"BoundingBox3D Extent X" : 4.0999999046325684,
			"BoundingBox3D Extent Y" : 2.0490226745605469,
			"BoundingBox3D Extent Z" : 1.7058093547821045,
			"BoundingBox3D Orientation Quat W" : 0.99949014186859131,
			"BoundingBox3D Orientation Quat X" : 0.024056272581219673,
			"BoundingBox3D Orientation Quat Y" : -0.0030498062260448933,
			"BoundingBox3D Orientation Quat Z" : 0.020566690713167191,
			"BoundingBox3D Origin X" : 21.666467666625977,
			"BoundingBox3D Origin Y" : -9.9829216003417969,
			"BoundingBox3D Origin Z" : 0.82885515689849854,
			"ObjectId" : 4,
			"ObjectType" : "CAR",
			"Occluded" : 0.0,
			"Relative Acceleration X" : 0.0082916375249624252,
			"Relative Acceleration Y" : 0.00020017940551042557,
			"Relative Acceleration Z" : -0.0010019912151619792,
			"Relative Velocity X" : 0.00021435628877952695,
			"Relative Velocity Y" : 0.0020388655830174685,
			"Relative Velocity Z" : -0.0012409357586875558,
			"Truncated" : 0
		},
		{
			"Absolute Acceleration X" : -0.0033189943060278893,
			"Absolute Acceleration Y" : -0.019961381331086159,
			"Absolute Acceleration Z" : 9.8211690783500671e-05,
			"Absolute Velocity X" : 0.015039178542792797,
			"Absolute Velocity Y" : -0.018051713705062866,
			"Absolute Velocity Z" : -0.0014099053805693984,
			"ActorName" : "PEDESTRIAN 05",
			"BoundingBox3D Extent X" : 1.0821120738983154,
			"BoundingBox3D Extent Y" : 0.92437934875488281,
			"BoundingBox3D Extent Z" : 1.8218027353286743,
			"BoundingBox3D Orientation Quat W" : 0.93843263387680054,
			"BoundingBox3D Orientation Quat X" : 0.016396462917327881,
			"BoundingBox3D Orientation Quat Y" : 0.0068066292442381382,
			"BoundingBox3D Orientation Quat Z" : -0.34485849738121033,
			"BoundingBox3D Origin X" : -30.356922149658203,
			"BoundingBox3D Origin Y" : 6.7713427543640137,
			"BoundingBox3D Origin Z" : 1.1445678472518921,
			"ObjectId" : 5,
			"ObjectType" : "PEDESTRIAN",
			"Occluded" : 0.0,
			"Relative Acceleration X" : 0.012703550979495049,
			"Relative Acceleration Y" : -0.024039730429649353,
			"Relative Acceleration Z" : 0.0050349738448858261,
			"Relative Velocity X" : 0.0086458567529916763,
			"Relative Velocity Y" : -0.015802927315235138,
			"Relative Velocity Z" : -0.0036692181602120399,
			"Truncated" : 0
		},
		{
			"Absolute Acceleration X" : -0.020669201388955116,
			"Absolute Acceleration Y" : 0.0039994753897190094,
			"Absolute Acceleration Z" : 0.001403438625857234,
			"Absolute Velocity X" : 0.0097004435956478119,
			"Absolute Velocity Y" : 0.008210599422454834,
			"Absolute Velocity Z" : -0.00090937252389267087,
			"ActorName" : "CAR 06",
			"BoundingBox3D Extent X" : 4.0999999046325684,
			"BoundingBox3D Extent Y" : 2.5505697727203369,
			"BoundingBox3D Extent Z" : 1.5177955627441406,
			"BoundingBox3D Orientation Quat W" : -0.99977034330368042,
			"BoundingBox3D Orientation Quat X" : 0.012480837292969227,
			"BoundingBox3D Orientation Quat Y" : -0.0025798485148698092,
			"BoundingBox3D Orientation Quat Z" : -0.0011608169879764318,
			"BoundingBox3D Origin X" : 24.478906631469727,
			"BoundingBox3D Origin Y" : -22.247976303100586,
			"BoundingBox3D Origin Z" : 0.87318551540374756,
			"ObjectId" : 6,
			"ObjectType" : "CAR",
			"Occluded" : 0.0,
			"Relative Acceleration X" : -0.0025005277711898088,
			"Relative Acceleration Y" : 0.0040435986593365669,
			"Relative Acceleration Z" : -0.0020218170247972012,
			"Relative Velocity X" : 0.002224393654614687,
			"Relative Velocity Y" : 0.008406447246670723,
			"Relative Velocity Z" : -0.0015979119343683124,
			"Truncated" : 0
		},
		{
			"Absolute Acceleration X" : -0.0093868058174848557,
			"Absolute Acceleration Y" : 0.076629519462585449,
			"Absolute Acceleration Z" : 0.00075550767360255122,
			"Absolute Velocity X" : 0.019354520365595818,
			"Absolute Velocity Y" : -0.011506566777825356,
			"Absolute Velocity Z" : -0.00015594420256093144,
			"ActorName" : "CAR 07",
			"BoundingBox3D Extent X" : 4.0999999046325684,
			"BoundingBox3D Extent Y" : 1.5989747047424316,
			"BoundingBox3D Extent Z" : 4.8014822006225586,
			"BoundingBox3D Orientation Quat W" : 0.99997478723526001,
			"BoundingBox3D Orientation Quat X" : 0.0046450337395071983,
			"BoundingBox3D Orientation Quat Y" : -0.00054832221940159798,
			"BoundingBox3D Orientation Quat Z" : -0.0053621083498001099,
			"BoundingBox3D Origin X" : 122.37948608398438,
			"BoundingBox3D Origin Y" : 5.0978059768676758,
			"BoundingBox3D Origin Z" : 3.7607955932617188,
			"ObjectId" : 7,
			"ObjectType" : "CAR",
			"Occluded" : 0.0,
			"Relative Acceleration X" : 0.0068871648982167244,
			"Relative Acceleration Y" : 0.083379946649074554,
			"Relative Acceleration Z" : -0.0021508724894374609,
			"Relative Velocity X" : 0.012759898789227009,
			"Relative Velocity Y" : -0.015135115943849087,
			"Relative Velocity Z" : 0.0056165219284594059,
			"Truncated" : 0
		},
		{
			"Absolute Acceleration X" : -0.0066327955573797226,
			"Absolute Acceleration Y" : 0.06381089985370636,
			"Absolute Acceleration Z" : -0.042839027941226959,
			"Absolute Velocity X" : 0.046370800584554672,
			"Absolute Velocity Y" : 0.078358188271522522,
			"Absolute Velocity Z" : -0.015015951357781887,
			"ActorName" : "CAR 09",
			"BoundingBox3D Extent X" : 4.0999999046325684,
			"BoundingBox3D Extent Y" : 1.4542628526687622,
			"BoundingBox3D Extent Z" : 1.4292941093444824,
			"BoundingBox3D Orientation Quat W" : 0.099566921591758728,
			"BoundingBox3D Orientation Quat X" : -0.00010847854719031602,
			"BoundingBox3D Orientation Quat Y" : -0.0046726367436349392,
			"BoundingBox3D Orientation Quat Z" : 0.99502027034759521,
			"BoundingBox3D Origin X" : 73.838119506835938,
			"BoundingBox3D Origin Y" : -9.7322521209716797,
			"BoundingBox3D Origin Z" : 0.91483777761459351,
			"ObjectId" : 9,
			"ObjectType" : "CAR",
			"Occluded" : 0.0,
			"Relative Acceleration X" : 0.010608667507767677,
			"Relative Acceleration Y" : 0.067515335977077484,
			"Relative Acceleration Z" : -0.046249359846115112,
			"Relative Velocity X" : 0.039364043623209,
			"Relative Velocity Y" : 0.076694011688232422,
			"Relative Velocity Z" : -0.012497212737798691,
			"Truncated" : 0
		},
		{
			"Absolute Acceleration X" : -0.094321727752685547,
			"Absolute Acceleration Y" : 0.1279846727848053,
			"Absolute Acceleration Z" : -0.02506566047668457,
			"Absolute Velocity X" : -1.4300382137298584,
			"Absolute Velocity Y" : -0.2819446325302124,
			"Absolute Velocity Z" : 0.018907194957137108,
			"ActorName" : "PEDESTRIAN 14",
			"BoundingBox3D Extent X" : 0.76351511478424072,
			"BoundingBox3D Extent Y" : 0.7488250732421875,
			"BoundingBox3D Extent Z" : 1.6945759057998657,
			"BoundingBox3D Orientation Quat W" : 0.011183075606822968,
			"BoundingBox3D Orientation Quat X" : 0.0048814956098794937,
			"BoundingBox3D Orientation Quat Y" : 0.0040739444084465504,
			"BoundingBox3D Orientation Quat Z" : 0.99969089031219482,
			"BoundingBox3D Origin X" : 32.538314819335938,
			"BoundingBox3D Origin Y" : 6.6662025451660156,
			"BoundingBox3D Origin Z" : 0.77918523550033569,
			"ObjectId" : 14,
			"ObjectType" : "PEDESTRIAN",
			"Occluded" : 0.0,
			"Relative Acceleration X" : -0.078322887420654297,
			"Relative Acceleration Y" : 0.12874281406402588,
			"Relative Acceleration Z" : -0.023179598152637482,
			"Relative Velocity X" : -1.4364098310470581,
			"Relative Velocity Y" : -0.28207850456237793,
			"Relative Velocity Z" : 0.020002402365207672,
			"Truncated" : 0
		},
		{
			"Absolute Acceleration X" : -0.2902769148349762,
			"Absolute Acceleration Y" : 0.0054496312513947487,
			"Absolute Acceleration Z" : -0.0014942163834348321,
			"Absolute Velocity X" : 0.47793272137641907,
			"Absolute Velocity Y" : 0.0074650635942816734,
			"Absolute Velocity Z" : 0.0020864072721451521,
			"ActorName" : "CAR 20",
			"BoundingBox3D Extent X" : 4.8109946250915527,
			"BoundingBox3D Extent Y" : 2.1602931022644043,
			"BoundingBox3D Extent Z" : 1.5548712015151978,
			"BoundingBox3D Orientation Quat W" : 0.99996805191040039,
			"BoundingBox3D Orientation Quat X" : 0.0023775931913405657,
			"BoundingBox3D Orientation Quat Y" : -0.0011437053326517344,
			"BoundingBox3D Orientation Quat Z" : -0.0085371397435665131,
			"BoundingBox3D Origin X" : -6.8895454406738281,
			"BoundingBox3D Origin Y" : -0.34233874082565308,
			"BoundingBox3D Origin Z" : 0.79229247570037842,
			"ObjectId" : 20,
			"ObjectType" : "CAR",
			"Occluded" : 0.0,
			"Relative Acceleration X" : -0.27374318242073059,
			"Relative Acceleration Y" : 0.0031428984366357327,
			"Relative Acceleration Z" : 0.00089194881729781628,
			"Relative Velocity X" : 0.47128993272781372,
			"Relative Velocity Y" : 0.0088555235415697098,
			"Relative Velocity Z" : 0.00072944624116644263,
			"Truncated" : 0
		},
		{
			"Absolute Acceleration X" : 0.068120382726192474,
			"Absolute Acceleration Y" : -0.043680388480424881,
			"Absolute Acceleration Z" : 0.0026904426049441099,
			"Absolute Velocity X" : 0.044977638870477676,
			"Absolute Velocity Y" : 0.0031742602586746216,
			"Absolute Velocity Z" : 0.002701812656596303,
			"ActorName" : "CAR 22",
			"BoundingBox3D Extent X" : 5.7580447196960449,
			"BoundingBox3D Extent Y" : 1.2421867847442627,
			"BoundingBox3D Extent Z" : 0.84952366352081299,
			"BoundingBox3D Orientation Quat W" : -0.996867835521698,
			"BoundingBox3D Orientation Quat X" : -0.0050458107143640518,
			"BoundingBox3D Orientation Quat Y" : 0.012433286756277084,
			"BoundingBox3D Orientation Quat Z" : 0.076757118105888367,
			"BoundingBox3D Origin X" : -51.518482208251953,
			"BoundingBox3D Origin Y" : -2.3580687046051025,
			"BoundingBox3D Origin Z" : 1.2113628387451172,
			"ObjectId" : 22,
			"ObjectType" : "CAR",
			"Occluded" : 0.0,
			"Relative Acceleration X" : 0.084820777177810669,
			"Relative Acceleration Y" : -0.04934190958738327,
			"Relative Acceleration Z" : 0.0068832770921289921,
			"Relative Velocity X" : 0.038239482790231705,
			"Relative Velocity Y" : 0.0062170708552002907,
			"Relative Velocity Z" : -0.0011018828954547644,
			"Truncated" : 0
		},
		{
			"Absolute Acceleration X" : 0.0079419659450650215,
			"Absolute Acceleration Y" : -0.010934866964817047,
			"Absolute Acceleration Z" : -2.3646174668101594e-05,
			"Absolute Velocity X" : 0.0024794857017695904,
			"Absolute Velocity Y" : -0.013405161909759045,
			"Absolute Velocity Z" : -3.6225752410246059e-05,
			"ActorName" : "CAR 26",
			"BoundingBox3D Extent X" : 4.1519966125488281,
			"BoundingBox3D Extent Y" : 1.4400417804718018,
			"BoundingBox3D Extent Z" : 1.3898543119430542,
			"BoundingBox3D Orientation Quat W" : -0.97813844680786133,
			"BoundingBox3D Orientation Quat X" : -0.0046564084477722645,
			"BoundingBox3D Orientation Quat Y" : -0.00040369239286519587,
			"BoundingBox3D Orientation Quat Z" : 0.20790120959281921,
			"BoundingBox3D Origin X" : 116.63590240478516,
			"BoundingBox3D Origin Y" : -10.220122337341309,
			"BoundingBox3D Origin Z" : 0.6073763370513916,
			"ObjectId" : 26,
			"ObjectType" : "CAR",
			"Occluded" : 0.0,
			"Relative Acceleration X" : 0.025201203301548958,
			"Relative Acceleration Y" : -0.0039944518357515335,
			"Relative Acceleration Z" : -0.0056443805806338787,
			"Relative Velocity X" : -0.0045243310742080212,
			"Relative Velocity Y" : -0.016671542078256607,
			"Relative Velocity Z" : 0.0047246241010725498,
			"Truncated" : 0
		},
		{
			"Absolute Acceleration X" : 0.010947264730930328,
			"Absolute Acceleration Y" : 0.052849382162094116,
			"Absolute Acceleration Z" : 0.00052134395809844136,
			"Absolute Velocity X" : 0.0029691979289054871,
			"Absolute Velocity Y" : -0.011792152188718319,
			"Absolute Velocity Z" : -0.00010899089102167636,
			"ActorName" : "CAR 27",
			"BoundingBox3D Extent X" : 4.0999999046325684,
			"BoundingBox3D Extent Y" : 0.49168747663497925,
			"BoundingBox3D Extent Z" : 5.5765342712402344,
			"BoundingBox3D Orientation Quat W" : 0.99998760223388672,
			"BoundingBox3D Orientation Quat X" : 0.0046397605910897255,
			"BoundingBox3D Orientation Quat Y" : -0.00058106175856664777,
			"BoundingBox3D Orientation Quat Z" : 0.0017024916596710682,
			"BoundingBox3D Origin X" : 87.297889709472656,
			"BoundingBox3D Origin Y" : -6.2504720687866211,
			"BoundingBox3D Origin Z" : 2.6107475757598877,
			"ObjectId" : 27,
			"ObjectType" : "CAR",
			"Occluded" : 0.0,
			"Relative Acceleration X" : 0.028007602319121361,
			"Relative Acceleration Y" : 0.057221058756113052,
			"Relative Acceleration Z" : -0.0028734877705574036,
			"Relative Velocity X" : -0.0039921686984598637,
			"Relative Velocity Y" : -0.01404592115432024,
			"Relative Velocity Z" : 0.0032768475357443094,
			"Truncated" : 0
		},
		{
			"Absolute Acceleration X" : -0.055919408798217773,
			"Absolute Acceleration Y" : 0.027101244777441025,
			"Absolute Acceleration Z" : 0.026191316545009613,
			"Absolute Velocity X" : 1.7100770473480225,
			"Absolute Velocity Y" : 0.022326305508613586,
			"Absolute Velocity Z" : -0.0060194055549800396,
			"ActorName" : "PEDESTRIAN 28",
			"BoundingBox3D Extent X" : 0.8595740795135498,
			"BoundingBox3D Extent Y" : 0.70261925458908081,
			"BoundingBox3D Extent Z" : 1.6828724145889282,
			"BoundingBox3D Orientation Quat W" : 0.99977511167526245,
			"BoundingBox3D Orientation Quat X" : -0.015029042027890682,
			"BoundingBox3D Orientation Quat Y" : 0.0010580738307908177,
			"BoundingBox3D Orientation Quat Z" : 0.014173728413879871,
			"BoundingBox3D Origin X" : 11.149289131164551,
			"BoundingBox3D Origin Y" : -6.8156366348266602,
			"BoundingBox3D Origin Z" : 0.83179157972335815,
			"ObjectId" : 28,
			"ObjectType" : "PEDESTRIAN",
			"Occluded" : 0.0,
			"Relative Acceleration X" : -0.038903951644897461,
			"Relative Acceleration Y" : 0.026052122935652733,
			"Relative Acceleration Z" : 0.026378829032182693,
			"Relative Velocity X" : 1.7031867504119873,
			"Relative Velocity Y" : 0.023058697581291199,
			"Relative Velocity Z" : -0.0067576323635876179,
			"Truncated" : 0
		},
		{
			"Absolute Acceleration X" : -0.022093039005994797,
			"Absolute Acceleration Y" : 0.00018172734417021275,
			"Absolute Acceleration Z" : -0.00065420783357694745,
			"Absolute Velocity X" : 0.013411266729235649,
			"Absolute Velocity Y" : -0.0011001293314620852,
			"Absolute Velocity Z" : -0.00061563705094158649,
			"ActorName" : "CAR 40",
			"BoundingBox3D Extent X" : 4.0999999046325684,
			"BoundingBox3D Extent Y" : 1.7546474933624268,
			"BoundingBox3D Extent Z" : 1.6427541971206665,
			"BoundingBox3D Orientation Quat W" : -0.710793137550354,
			"BoundingBox3D Orientation Quat X" : 0.013281457126140594,
			"BoundingBox3D Orientation Quat Y" : 0.0085834451019763947,
			"BoundingBox3D Orientation Quat Z" : 0.70293611288070679,
			"BoundingBox3D Origin X" : 20.543487548828125,
			"BoundingBox3D Origin Y" : -22.896247863769531,
			"BoundingBox3D Origin Z" : 0.97228509187698364,
			"ObjectId" : 40,
			"ObjectType" : "CAR",
			"Occluded" : 0.0,
			"Relative Acceleration X" : -0.0038760751485824585,
			"Relative Acceleration Y" : -8.5765495896339417e-05,
			"Relative Acceleration Z" : -0.0040126941166818142,
			"Relative Velocity X" : 0.0059087201952934265,
			"Relative Velocity Y" : -0.00076068053022027016,
			"Relative Velocity Z" : -0.0015440331771969795,
			"Truncated" : 0
		},
		{
			"Absolute Acceleration X" : 0.033748380839824677,
			"Absolute Acceleration Y" : 0.017715385183691978,
			"Absolute Acceleration Z" : 0.0024324464611709118,
			"Absolute Velocity X" : -0.073530063033103943,
			"Absolute Velocity Y" : -0.052532874047756195,
			"Absolute Velocity Z" : 0.0070004938170313835,
			"ActorName" : "CAR 42",
			"BoundingBox3D Extent X" : 4.3062043190002441,
			"BoundingBox3D Extent Y" : 1.461146354675293,
			"BoundingBox3D Extent Z" : 1.5511000156402588,
			"BoundingBox3D Orientation Quat W" : 0.1020437628030777,
			"BoundingBox3D Orientation Quat X" : -0.0061146407388150692,
			"BoundingBox3D Orientation Quat Y" : 0.048280652612447739,
			"BoundingBox3D Orientation Quat Z" : 0.9935765266418457,
			"BoundingBox3D Origin X" : -28.224422454833984,
			"BoundingBox3D Origin Y" : -3.2331256866455078,
			"BoundingBox3D Origin Z" : 0.78004562854766846,
			"ObjectId" : 42,
			"ObjectType" : "CAR",
			"Occluded" : 0.0,
			"Relative Acceleration X" : 0.050495579838752747,
			"Relative Acceleration Y" : 0.013871246948838234,
			"Relative Acceleration Z" : 0.0053162281401455402,
			"Relative Velocity X" : -0.080279640853404999,
			"Relative Velocity Y" : -0.050350718200206757,
			"Relative Velocity Z" : 0.0043923310004174709,
			"Truncated" : 0
		},
		{
			"Absolute Acceleration X" : -0.016655683517456055,
			"Absolute Acceleration Y" : 0.00051831308519467711,
			"Absolute Acceleration Z" : 8.2550744991749525e-05,
			"Absolute Velocity X" : 0.0084627419710159302,
			"Absolute Velocity Y" : 0.00015734149201307446,
			"Absolute Velocity Z" : -0.0001534504845039919,
			"ActorName" : "CAR 45",
			"BoundingBox3D Extent X" : 4.4129219055175781,
			"BoundingBox3D Extent Y" : 1.7963695526123047,
			"BoundingBox3D Extent Z" : 1.7314826250076294,
			"BoundingBox3D Orientation Quat W" : 0.99979710578918457,
			"BoundingBox3D Orientation Quat X" : -0.0023700839374214411,
			"BoundingBox3D Orientation Quat Y" : 0.0031295039225369692,
			"BoundingBox3D Orientation Quat Z" : 0.019385162740945816,
			"BoundingBox3D Origin X" : 9.2399835586547852,
			"BoundingBox3D Origin Y" : 0.056407097727060318,
			"BoundingBox3D Origin Z" : 0.81936544179916382,
			"ObjectId" : 45,
			"ObjectType" : "CAR",
			"Occluded" : 0.0,
			"Relative Acceleration X" : -0.00015038822311908007,
			"Relative Acceleration Y" : -0.00055683095706626773,
			"Relative Acceleration Z" : 0.0017603029264137149,
			"Relative Velocity X" : 0.0018334442283958197,
			"Relative Velocity Y" : 0.00092870974913239479,
			"Relative Velocity Z" : -0.00061938381986692548,
			"Truncated" : 0
		},
		{
			"Absolute Acceleration X" : -0.019136073067784309,
			"Absolute Acceleration Y" : 0.00089964433573186398,
			"Absolute Acceleration Z" : -0.00044947434798814356,
			"Absolute Velocity X" : -0.0012063590111210942,
			"Absolute Velocity Y" : 0.00059215084183961153,
			"Absolute Velocity Z" : 1.276534385397099e-05,
			"ActorName" : "CAR 48",
			"BoundingBox3D Extent X" : 5.1649026870727539,
			"BoundingBox3D Extent Y" : 2.8514852523803711,
			"BoundingBox3D Extent Z" : 2.7886321544647217,
			"BoundingBox3D Orientation Quat W" : -0.041587412357330322,
			"BoundingBox3D Orientation Quat X" : -0.0022150222212076187,
			"BoundingBox3D Orientation Quat Y" : -0.0028953081928193569,
			"BoundingBox3D Orientation Quat Z" : 0.99911683797836304,
			"BoundingBox3D Origin X" : 16.680980682373047,
			"BoundingBox3D Origin Y" : -8.0065193176269531,
			"BoundingBox3D Origin Z" : 1.4475175142288208,
			"ObjectId" : 48,
			"ObjectType" : "CAR",
			"Occluded" : 0.0,
			"Relative Acceleration X" : -0.0020009898580610752,
			"Relative Acceleration Y" : 0.00025465106591582298,
			"Relative Acceleration Z" : -0.0007115931948646903,
			"Relative Velocity X" : -0.008173041045665741,
			"Relative Velocity Y" : 0.0010539795039221644,
			"Relative Velocity Z" : -0.0004313281096983701,
			"Truncated" : 0
		},
		{
			"Absolute Acceleration X" : 0.039149045944213867,
			"Absolute Acceleration Y" : -0.11826188117265701,
			"Absolute Acceleration Z" : 0.0071074506267905235,
			"Absolute Velocity X" : -1.1025139093399048,
			"Absolute Velocity Y" : -0.072993755340576172,
			"Absolute Velocity Z" : -0.00076935428660362959,
			"ActorName" : "PEDESTRIAN 49",
			"BoundingBox3D Extent X" : 0.74886947870254517,
			"BoundingBox3D Extent Y" : 1.1408140659332275,
			"BoundingBox3D Extent Z" : 1.7221313714981079,
			"BoundingBox3D Orientation Quat W" : -0.056669939309358597,
			"BoundingBox3D Orientation Quat X" : -0.0039801318198442459,
			"BoundingBox3D Orientation Quat Y" : -0.017720291391015053,
			"BoundingBox3D Orientation Quat Z" : 0.99818694591522217,
			"BoundingBox3D Origin X" : 38.767971038818359,
			"BoundingBox3D Origin Y" : 7.3251919746398926,
			"BoundingBox3D Origin Z" : 0.61366599798202515,
			"ObjectId" : 49,
			"ObjectType" : "PEDESTRIAN",
			"Occluded" : 0.0,
			"Relative Acceleration X" : 0.055105328559875488,
			"Relative Acceleration Y" : -0.11703234910964966,
			"Relative Acceleration Z" : 0.0087739275768399239,
			"Relative Velocity X" : -1.1088581085205078,
			"Relative Velocity Y" : -0.073348052799701691,
			"Relative Velocity Z" : 0.00069873227039352059,
			"Truncated" : 0
		},
		{
			"Absolute Acceleration X" : 0.077008366584777832,
			"Absolute Acceleration Y" : 0.15028637647628784,
			"Absolute Acceleration Z" : 0.047213807702064514,
			"Absolute Velocity X" : -0.046717729419469833,
			"Absolute Velocity Y" : -0.050003811717033386,
			"Absolute Velocity Z" : -0.0004926392575725913,
			"ActorName" : "CAR 53",
			"BoundingBox3D Extent X" : 4.0999999046325684,
			"BoundingBox3D Extent Y" : 2.428370475769043,
			"BoundingBox3D Extent Z" : 6.8031253814697266,
			"BoundingBox3D Orientation Quat W" : -0.94914418458938599,
			"BoundingBox3D Orientation Quat X" : -0.0045838020741939545,
			"BoundingBox3D Orientation Quat Y" : -0.00091637152945622802,
			"BoundingBox3D Orientation Quat Z" : 0.31480711698532104,
			"BoundingBox3D Origin X" : 142.99270629882812,
			"BoundingBox3D Origin Y" : -6.451927661895752,
			"BoundingBox3D Origin Z" : 3.7153434753417969,
			"ObjectId" : 53,
			"ObjectType" : "CAR",
			"Occluded" : 0.0,
			"Relative Acceleration X" : 0.094134986400604248,
			"Relative Acceleration Y" : 0.15857519209384918,
			"Relative Acceleration Z" : 0.041043132543563843,
			"Relative Velocity X" : -0.053742390125989914,
			"Relative Velocity Y" : -0.054409671574831009,
			"Relative Velocity Z" : 0.0058422889560461044,
			"Truncated" : 0
		},
		{
			"Absolute Acceleration X" : -0.1395149827003479,
			"Absolute Acceleration Y" : 0.03743421658873558,
			"Absolute Acceleration Z" : -0.030913259834051132,
			"Absolute Velocity X" : 0.043875295668840408,
			"Absolute Velocity Y" : -0.007207358255982399,
			"Absolute Velocity Z" : 0.0072400271892547607,
			"ActorName" : "CAR 54",
			"BoundingBox3D Extent X" : 4.2212715148925781,
			"BoundingBox3D Extent Y" : 1.6966679096221924,
			"BoundingBox3D Extent Z" : 0.61417239904403687,
			"BoundingBox3D Orientation Quat W" : 0.99979531764984131,
			"BoundingBox3D Orientation Quat X" : 0.0046489732339978218,
			"BoundingBox3D Orientation Quat Y" : -0.0004818964225705713,
			"BoundingBox3D Orientation Quat Z" : -0.019668687134981155,
			"BoundingBox3D Origin X" : 47.158237457275391,
			"BoundingBox3D Origin Y" : -33.011524200439453,
			"BoundingBox3D Origin Z" : 1.2286703586578369,
			"ObjectId" : 54,
			"ObjectType" : "CAR",
			"Occluded" : 0.0,
			"Relative Acceleration X" : -0.1205378994345665,
			"Relative Acceleration Y" : 0.039093594998121262,
			"Relative Acceleration Z" : -0.037550158798694611,
			"Relative Velocity X" : 0.035978727042675018,
			"Relative Velocity Y" : -0.0078826220706105232,
			"Relative Velocity Z" : 0.0072531611658632755,
			"Truncated" : 0
		},
		{
			"Absolute Acceleration X" : -0.022630397230386734,
			"Absolute Acceleration Y" : -0.081847153604030609,
			"Absolute Acceleration Z" : -0.099680647253990173,
			"Absolute Velocity X" : 0.013998757116496563,
			"Absolute Velocity Y" : 0.028832700103521347,
			"Absolute Velocity Z" : -0.014883946627378464,
			"ActorName" : "CAR 55",
			"BoundingBox3D Extent X" : 4.2007722854614258,
			"BoundingBox3D Extent Y" : 2.2973442077636719,
			"BoundingBox3D Extent Z" : 1.1088563203811646,
			"BoundingBox3D Orientation Quat W" : -0.9988858699798584,
			"BoundingBox3D Orientation Quat X" : -0.0046069077216088772,
			"BoundingBox3D Orientation Quat Y" : 0.00078830664278939366,
			"BoundingBox3D Orientation Quat Z" : -0.046957924962043762,
			"BoundingBox3D Origin X" : 46.58062744140625,
			"BoundingBox3D Origin Y" : -16.623989105224609,
			"BoundingBox3D Origin Z" : 0.67982339859008789,
			"ObjectId" : 55,
			"ObjectType" : "CAR",
			"Occluded" : 0.0,
			"Relative Acceleration X" : -0.0048945639282464981,
			"Relative Acceleration Y" : -0.080115556716918945,
			"Relative Acceleration Z" : -0.10310585051774979,
			"Relative Velocity X" : 0.0067465761676430702,
			"Relative Velocity Y" : 0.028208013623952866,
			"Relative Velocity Z" : -0.014139226637780666,
			"Truncated" : 0
		},
		{
			"Absolute Acceleration X" : -0.001902606338262558,
			"Absolute Acceleration Y" : 0.035937443375587463,
			"Absolute Acceleration Z" : 0.050564728677272797,
			"Absolute Velocity X" : -0.021379262208938599,
			"Absolute Velocity Y" : 0.011037733405828476,
			"Absolute Velocity Z" : -0.018009472638368607,
			"ActorName" : "CAR 56",
			"BoundingBox3D Extent X" : 4.0999999046325684,
			"BoundingBox3D Extent Y" : 1.3321907520294189,
			"BoundingBox3D Extent Z" : 0.97723209857940674,
			"BoundingBox3D Orientation Quat W" : 0.93242758512496948,
			"BoundingBox3D Orientation Quat X" : 0.004532612394541502,
			"BoundingBox3D Orientation Quat Y" : 0.0011416879715397954,
			"BoundingBox3D Orientation Quat Z" : -0.36132603883743286,
			"BoundingBox3D Origin X" : 25.620691299438477,
			"BoundingBox3D Origin Y" : -47.234939575195312,
			"BoundingBox3D Origin Z" : 1.0046392679214478,
			"ObjectId" : 56,
			"ObjectType" : "CAR",
			"Occluded" : 0.0,
			"Relative Acceleration X" : 0.018122861161828041,
			"Relative Acceleration Y" : 0.036040104925632477,
			"Relative Acceleration Z" : 0.042210694402456284,
			"Relative Velocity X" : -0.029801890254020691,
			"Relative Velocity Y" : 0.011183678172528744,
			"Relative Velocity Z" : -0.019791388884186745,
			"Truncated" : 0
		},
		{
			"Absolute Acceleration X" : 4.3817199184559286e-05,
			"Absolute Acceleration Y" : -7.3788287409115583e-05,
			"Absolute Acceleration Z" : -6.4164196373894811e-06,
			"Absolute Velocity X" : 3.103377457591705e-05,
			"Absolute Velocity Y" : -0.00014711444964632392,
			"Absolute Velocity Z" : 7.5245702646498103e-06,
			"ActorName" : "CAR 57",
			"BoundingBox3D Extent X" : 2.2044937610626221,
			"BoundingBox3D Extent Y" : 1.8999999761581421,
			"BoundingBox3D Extent Z" : 2.2563025951385498,
			"BoundingBox3D Orientation Quat W" : -0.6950608491897583,
			"BoundingBox3D Orientation Quat X" : -0.0042971344664692879,
			"BoundingBox3D Orientation Quat Y" : -0.0035990194883197546,
			"BoundingBox3D Orientation Quat Z" : 0.71774852275848389,
			"BoundingBox3D Origin X" : 98.183639526367188,
			"BoundingBox3D Origin Y" : -49.828857421875,
			"BoundingBox3D Origin Z" : 2.6611361503601074,
			"ObjectId" : 57,
			"ObjectType" : "CAR",
			"Occluded" : 0.0,
			"Relative Acceleration X" : 0.020344160497188568,
			"Relative Acceleration Y" : 0.0050958758220076561,
			"Relative Acceleration Z" : -0.012446233071386814,
			"Relative Velocity X" : -0.0085766613483428955,
			"Relative Velocity Y" : -0.0028126908000558615,
			"Relative Velocity Z" : 0.0019555909093469381,
			"Truncated" : 0
		},
		{
			"Absolute Acceleration X" : -0.019663926213979721,
			"Absolute Acceleration Y" : -0.0099092172458767891,
			"Absolute Acceleration Z" : 0.0032296048011630774,
			"Absolute Velocity X" : 0.0030142907053232193,
			"Absolute Velocity Y" : 0.0054176324047148228,
			"Absolute Velocity Z" : 0.00075145123992115259,
			"ActorName" : "CAR 58",
			"BoundingBox3D Extent X" : 4.0999999046325684,
			"BoundingBox3D Extent Y" : 1.513579249382019,
			"BoundingBox3D Extent Z" : 0.91176110506057739,
			"BoundingBox3D Orientation Quat W" : -0.79598218202590942,
			"BoundingBox3D Orientation Quat X" : -0.0025576262269169092,
			"BoundingBox3D Orientation Quat Y" : 0.024101575836539268,
			"BoundingBox3D Orientation Quat Z" : 0.60441726446151733,
			"BoundingBox3D Origin X" : 13.781365394592285,
			"BoundingBox3D Origin Y" : -27.717554092407227,
			"BoundingBox3D Origin Z" : 0.65755200386047363,
			"ObjectId" : 58,
			"ObjectType" : "CAR",
			"Occluded" : 0.0,
			"Relative Acceleration X" : -0.0011039848905056715,
			"Relative Acceleration Y" : -0.010616583749651909,
			"Relative Acceleration Z" : -0.00073717453051358461,
			"Relative Velocity X" : -0.0046532959677278996,
			"Relative Velocity Y" : 0.006025990005582571,
			"Relative Velocity Z" : -0.00075816520256921649,
			"Truncated" : 0
		},
		{
			"Absolute Acceleration X" : -0.010288774967193604,
			"Absolute Acceleration Y" : -0.016142889857292175,
			"Absolute Acceleration Z" : 0.0004151219327468425,
			"Absolute Velocity X" : 0.0070117590948939323,
			"Absolute Velocity Y" : 0.0072426507249474525,
			"Absolute Velocity Z" : -0.00013248581672087312,
			"ActorName" : "CAR 59",
			"BoundingBox3D Extent X" : 4.4756669998168945,
			"BoundingBox3D Extent Y" : 1.8517172336578369,
			"BoundingBox3D Extent Z" : 1.6542752981185913,
			"BoundingBox3D Orientation Quat W" : 0.71131283044815063,
			"BoundingBox3D Orientation Quat X" : -0.018527612090110779,
			"BoundingBox3D Orientation Quat Y" : 0.0013812823453918099,
			"BoundingBox3D Orientation Quat Z" : -0.70223170518875122,
			"BoundingBox3D Origin X" : 15.385861396789551,
			"BoundingBox3D Origin Y" : -23.094812393188477,
			"BoundingBox3D Origin Z" : 1.019686222076416,
			"ObjectId" : 59,
			"ObjectType" : "CAR",
			"Occluded" : 0.0,
			"Relative Acceleration X" : 0.0079458504915237427,
			"Relative Acceleration Y" : -0.016800321638584137,
			"Relative Acceleration Z" : -0.0027295355685055256,
			"Relative Velocity X" : -0.00050103734247386456,
			"Relative Velocity Y" : 0.0077730976045131683,
			"Relative Velocity Z" : -0.0013429125538095832,
			"Truncated" : 0
		},
		{
			"Absolute Acceleration X" : 0.0080355154350399971,
			"Absolute Acceleration Y" : -0.0026932843029499054,
			"Absolute Acceleration Z" : -0.016295528039336205,
			"Absolute Velocity X" : -0.0071915076114237309,
			"Absolute Velocity Y" : 0.027124745771288872,
			"Absolute Velocity Z" : -0.011432030238211155,
			"ActorName" : "PEDESTRIAN 60",
			"BoundingBox3D Extent X" : 0.72116613388061523,
			"BoundingBox3D Extent Y" : 0.5865478515625,
			"BoundingBox3D Extent Z" : 1.6632136106491089,
			"BoundingBox3D Orientation Quat W" : 0.95970922708511353,
			"BoundingBox3D Orientation Quat X" : 0.0042907032184302807,
			"BoundingBox3D Orientation Quat Y" : -0.0018533541588112712,
			"BoundingBox3D Orientation Quat Z" : 0.28093737363815308,
			"BoundingBox3D Origin X" : 57.954978942871094,
			"BoundingBox3D Origin Y" : 16.848127365112305,
			"BoundingBox3D Origin Z" : 0.69206809997558594,
			"ObjectId" : 60,
			"ObjectType" : "PEDESTRIAN",
			"Occluded" : 0.0,
			"Relative Acceleration X" : 0.02328915148973465,
			"Relative Acceleration Y" : -0.00012388452887535095,
			"Relative Acceleration Z" : -0.013742130249738693,
			"Relative Velocity X" : -0.013181899674236774,
			"Relative Velocity Y" : 0.026066254824399948,
			"Relative Velocity Z" : -0.0085307545959949493,
			"Truncated" : 0
		},
		{
			"Absolute Acceleration X" : -0.10942883789539337,
			"Absolute Acceleration Y" : -0.015105368569493294,
			"Absolute Acceleration Z" : -0.0027511981315910816,
			"Absolute Velocity X" : 0.010494759306311607,
			"Absolute Velocity Y" : -0.0033769023139029741,
			"Absolute Velocity Z" : -0.00012637427425943315,
			"ActorName" : "CAR 63",
			"BoundingBox3D Extent X" : 4.0999999046325684,
			"BoundingBox3D Extent Y" : 1.5583558082580566,
			"BoundingBox3D Extent Z" : 1.4409756660461426,
			"BoundingBox3D Orientation Quat W" : -0.99942785501480103,
			"BoundingBox3D Orientation Quat X" : 0.0065683433786034584,
			"BoundingBox3D Orientation Quat Y" : 0.023650649935007095,
			"BoundingBox3D Orientation Quat Z" : 0.022489918395876884,
			"BoundingBox3D Origin X" : 31.275104522705078,
			"BoundingBox3D Origin Y" : -26.472370147705078,
			"BoundingBox3D Origin Z" : 0.63689291477203369,
			"ObjectId" : 63,
			"ObjectType" : "CAR",
			"Occluded" : 0.0,
			"Relative Acceleration X" : -0.090960666537284851,
			"Relative Acceleration Y" : -0.014511848799884319,
			"Relative Acceleration Z" : -0.0073344316333532333,
			"Relative Velocity X" : 0.0028736998792737722,
			"Relative Velocity Y" : -0.0034260964021086693,
			"Relative Velocity Z" : -0.00065092241857200861,
			"Truncated" : 0
		},
		{
			"Absolute Acceleration X" : -0.016481809318065643,
			"Absolute Acceleration Y" : 0.0098808249458670616,
			"Absolute Acceleration Z" : -0.012791462242603302,
			"Absolute Velocity X" : 0.01545436680316925,
			"Absolute Velocity Y" : -0.0044798082672059536,
			"Absolute Velocity Z" : 5.8831366914091632e-05,
			"ActorName" : "CAR 64",
			"BoundingBox3D Extent X" : 4.0999999046325684,
			"BoundingBox3D Extent Y" : 0.59965306520462036,
			"BoundingBox3D Extent Z" : 2.0092730522155762,
			"BoundingBox3D Orientation Quat W" : -0.82091981172561646,
			"BoundingBox3D Orientation Quat X" : 0.014624465256929398,
			"BoundingBox3D Orientation Quat Y" : -0.011483075097203255,
			"BoundingBox3D Orientation Quat Z" : 0.57073885202407837,
			"BoundingBox3D Origin X" : 8.7179346084594727,
			"BoundingBox3D Origin Y" : -18.304306030273438,
			"BoundingBox3D Origin Z" : 1.1381868124008179,
			"ObjectId" : 64,
			"ObjectType" : "CAR",
			"Occluded" : 0.0,
			"Relative Acceleration X" : 0.00140371173620224,
			"Relative Acceleration Y" : 0.0087058395147323608,
			"Relative Acceleration Z" : -0.014670095406472683,
			"Relative Velocity X" : 0.0081148324534296989,
			"Relative Velocity Y" : -0.0037031625397503376,
			"Relative Velocity Z" : -0.0012852620566263795,
			"Truncated" : 0
		},
		{
			"Absolute Acceleration X" : -0.011704731732606888,
			"Absolute Acceleration Y" : -0.019253414124250412,
			"Absolute Acceleration Z" : -0.003527532797306776,
			"Absolute Velocity X" : 0.013963319361209869,
			"Absolute Velocity Y" : -2.4119686713675037e-05,
			"Absolute Velocity Z" : 0.00098207860719412565,
			"ActorName" : "PEDESTRIAN 65",
			"BoundingBox3D Extent X" : 0.73352646827697754,
			"BoundingBox3D Extent Y" : 0.55552083253860474,
			"BoundingBox3D Extent Z" : 1.0367329120635986,
			"BoundingBox3D Orientation Quat W" : -0.48603862524032593,
			"BoundingBox3D Orientation Quat X" : -0.070048980414867401,
			"BoundingBox3D Orientation Quat Y" : -0.028603339567780495,
			"BoundingBox3D Orientation Quat Z" : 0.87060654163360596,
			"BoundingBox3D Origin X" : 27.84290885925293,
			"BoundingBox3D Origin Y" : 17.233701705932617,
			"BoundingBox3D Origin Z" : 0.50256633758544922,
			"ObjectId" : 65,
			"ObjectType" : "PEDESTRIAN",
			"Occluded" : 0.0,
			"Relative Acceleration X" : 0.0035106469877064228,
			"Relative Acceleration Y" : -0.018885258585214615,
			"Relative Acceleration Z" : 0.00058337865630164742,
			"Relative Velocity X" : 0.0079976143315434456,
			"Relative Velocity Y" : 6.0108577599748969e-05,
			"Relative Velocity Z" : 0.0022983662784099579,
			"Truncated" : 0
		},
		{
			"Absolute Acceleration X" : -0.038055777549743652,
			"Absolute Acceleration Y" : -0.082976818084716797,
			"Absolute Acceleration Z" : -0.065446861088275909,
			"Absolute Velocity X" : 1.3746423721313477,
			"Absolute Velocity Y" : 0.28110232949256897,
			"Absolute Velocity Z" : 0.0078542614355683327,
			"ActorName" : "PEDESTRIAN 69",
			"BoundingBox3D Extent X" : 0.71067702770233154,
			"BoundingBox3D Extent Y" : 0.68047791719436646,
			"BoundingBox3D Extent Z" : 1.6571527719497681,
			"BoundingBox3D Orientation Quat W" : 0.99014180898666382,
			"BoundingBox3D Orientation Quat X" : 0.021621536463499069,
			"BoundingBox3D Orientation Quat Y" : 0.0080555034801363945,
			"BoundingBox3D Orientation Quat Z" : 0.12741637229919434,
			"BoundingBox3D Origin X" : 54.102069854736328,
			"BoundingBox3D Origin Y" : 15.162687301635742,
			"BoundingBox3D Origin Z" : 0.73641985654830933,
			"ObjectId" : 69,
			"ObjectType" : "PEDESTRIAN",
			"Occluded" : 0.0,
			"Relative Acceleration X" : -0.022657394409179688,
			"Relative Acceleration Y" : -0.08078138530254364,
			"Relative Acceleration Z" : -0.063083842396736145,
			"Relative Velocity X" : 1.3685840368270874,
			"Relative Velocity Y" : 0.28021278977394104,
			"Relative Velocity Z" : 0.010454348288476467,
			"Truncated" : 0
		},
		{
			"Absolute Acceleration X" : -0.037382617592811584,
			"Absolute Acceleration Y" : -0.0085314586758613586,
			"Absolute Acceleration Z" : 8.7805135990493e-05,
			"Absolute Velocity X" : -0.072902984917163849,
			"Absolute Velocity Y" : 0.027757035568356514,
			"Absolute Velocity Z" : 0.00079927471233531833,
			"ActorName" : "PEDESTRIAN 71",
			"BoundingBox3D Extent X" : 0.69999998807907104,
			"BoundingBox3D Extent Y" : 0.66917711496353149,
			"BoundingBox3D Extent Z" : 1.6532086133956909,
			"BoundingBox3D Orientation Quat W" : 0.90949225425720215,
			"BoundingBox3D Orientation Quat X" : 0.0071372739039361477,
			"BoundingBox3D Orientation Quat Y" : -0.00048707120004110038,
			"BoundingBox3D Orientation Quat Z" : 0.41564196348190308,
			"BoundingBox3D Origin X" : 8.8296852111816406,
			"BoundingBox3D Origin Y" : 6.2990484237670898,
			"BoundingBox3D Origin Z" : 0.91116565465927124,
			"ObjectId" : 71,
			"ObjectType" : "PEDESTRIAN",
			"Occluded" : 0.0,
			"Relative Acceleration X" : -0.021335449069738388,
			"Relative Acceleration Y" : -0.0096529675647616386,
			"Relative Acceleration Z" : 0.003005125792697072,
			"Relative Velocity X" : -0.079302422702312469,
			"Relative Velocity Y" : 0.028538104146718979,
			"Relative Velocity Z" : 0.00060571625363081694,
			"Truncated" : 0
		},
		{
			"Absolute Acceleration X" : -0.13834750652313232,
			"Absolute Acceleration Y" : 0.26109093427658081,
			"Absolute Acceleration Z" : 0.039015263319015503,
			"Absolute Velocity X" : 1.4897404909133911,
			"Absolute Velocity Y" : 0.0076805120334029198,
			"Absolute Velocity Z" : -0.063123136758804321,
			"ActorName" : "PEDESTRIAN 72",
			"BoundingBox3D Extent X" : 0.72116613388061523,
			"BoundingBox3D Extent Y" : 0.63140344619750977,
			"BoundingBox3D Extent Z" : 1.6509535312652588,
			"BoundingBox3D Orientation Quat W" : 0.99802219867706299,
			"BoundingBox3D Orientation Quat X" : -0.0014989495975896716,
			"BoundingBox3D Orientation Quat Y" : 0.010031276382505894,
			"BoundingBox3D Orientation Quat Z" : 0.05193043127655983,
			"BoundingBox3D Origin X" : 61.535240173339844,
			"BoundingBox3D Origin Y" : 15.278931617736816,
			"BoundingBox3D Origin Z" : 0.68499040603637695,
			"ObjectId" : 72,
			"ObjectType" : "PEDESTRIAN",
			"Occluded" : 0.0,
			"Relative Acceleration X" : -0.12298679351806641,
			"Relative Acceleration Y" : 0.26382321119308472,
			"Relative Acceleration Z" : 0.041065312922000885,
			"Relative Velocity X" : 1.4836891889572144,
			"Relative Velocity Y" : 0.0065213176421821117,
			"Relative Velocity Z" : -0.060156948864459991,
			"Truncated" : 0
		},
		{
			"Absolute Acceleration X" : -0.011595958843827248,
			"Absolute Acceleration Y" : -0.016942335292696953,
			"Absolute Acceleration Z" : 0.012368565425276756,
			"Absolute Velocity X" : -0.0051663615740835667,
			"Absolute Velocity Y" : 0.0048977243714034557,
			"Absolute Velocity Z" : 0.14503020048141479,
			"ActorName" : "CAR 73",
			"BoundingBox3D Extent X" : 4.199160099029541,
			"BoundingBox3D Extent Y" : 1.3334075212478638,
			"BoundingBox3D Extent Z" : 0.59362602233886719,
			"BoundingBox3D Orientation Quat W" : 0.9986308217048645,
			"BoundingBox3D Orientation Quat X" : 0.0046350541524589062,
			"BoundingBox3D Orientation Quat Y" : -0.00040131813148036599,
			"BoundingBox3D Orientation Quat Z" : -0.02444891445338726,
			"BoundingBox3D Origin X" : -38.966743469238281,
			"BoundingBox3D Origin Y" : -2.9641411304473877,
			"BoundingBox3D Origin Z" : 1.5914618968963623,
			"ObjectId" : 73,
			"ObjectType" : "CAR",
			"Occluded" : 0.0,
			"Relative Acceleration X" : 0.0051727709360420704,
			"Relative Acceleration Y" : -0.021748688071966171,
			"Relative Acceleration Z" : 0.015830114483833313,
			"Relative Velocity X" : -0.011949635110795498,
			"Relative Velocity Y" : 0.0074323881417512894,
			"Relative Velocity Z" : 0.14186537265777588,
			"Truncated" : 0
		},
		{
			"Absolute Acceleration X" : -0.019054898992180824,
			"Absolute Acceleration Y" : -0.0022332444787025452,
			"Absolute Acceleration Z" : 0.0057008266448974609,
			"Absolute Velocity X" : 6.2967170379124582e-05,
			"Absolute Velocity Y" : -0.067557498812675476,
			"Absolute Velocity Z" : 0.0035058720968663692,
			"ActorName" : "CAR 74",
			"BoundingBox3D Extent X" : 4.0999999046325684,
			"BoundingBox3D Extent Y" : 1.7633994817733765,
			"BoundingBox3D Extent Z" : 1.4396065473556519,
			"BoundingBox3D Orientation Quat W" : -0.99956268072128296,
			"BoundingBox3D Orientation Quat X" : -0.0040707113221287727,
			"BoundingBox3D Orientation Quat Y" : -0.029013505205512047,
			"BoundingBox3D Orientation Quat Z" : 9.3870730779599398e-05,
			"BoundingBox3D Origin X" : 16.514102935791016,
			"BoundingBox3D Origin Y" : -10.878010749816895,
			"BoundingBox3D Origin Z" : 0.59551805257797241,
			"ObjectId" : 74,
			"ObjectType" : "CAR",
			"Occluded" : 0.0,
			"Relative Acceleration X" : -0.0017482872353866696,
			"Relative Acceleration Y" : -0.0027232281863689423,
			"Relative Acceleration Z" : 0.0048861876130104065,
			"Relative Velocity X" : -0.0069669228978455067,
			"Relative Velocity Y" : -0.067051723599433899,
			"Relative Velocity Z" : 0.0029135248623788357,
			"Truncated" : 0
		},
		{
			"Absolute Acceleration X" : -0.011955587193369865,
			"Absolute Acceleration Y" : 0.018445026129484177,
			"Absolute Acceleration Z" : 0.00020438845967873931,
			"Absolute Velocity X" : -0.006489854771643877,
			"Absolute Velocity Y" : -0.023347470909357071,
			"Absolute Velocity Z" : -0.00077724276343360543,
			"ActorName" : "PEDESTRIAN 75",
			"BoundingBox3D Extent X" : 0.69999998807907104,
			"BoundingBox3D Extent Y" : 0.59953218698501587,
			"BoundingBox3D Extent Z" : 1.7113051414489746,
			"BoundingBox3D Orientation Quat W" : 0.49627363681793213,
			"BoundingBox3D Orientation Quat X" : 0.0083550279960036278,
			"BoundingBox3D Orientation Quat Y" : -0.0077984100207686424,
			"BoundingBox3D Orientation Quat Z" : 0.86809045076370239,
			"BoundingBox3D Origin X" : -8.3372907638549805,
			"BoundingBox3D Origin Y" : 6.5582647323608398,
			"BoundingBox3D Origin Z" : 1.021918773651123,
			"ObjectId" : 75,
			"ObjectType" : "PEDESTRIAN",
			"Occluded" : 0.0,
			"Relative Acceleration X" : 0.004075066652148962,
			"Relative Acceleration Y" : 0.01602589339017868,
			"Relative Acceleration Z" : 0.0040189642459154129,
			"Relative Velocity X" : -0.012884367257356644,
			"Relative Velocity Y" : -0.02192331850528717,
			"Relative Velocity Z" : -0.001877155271358788,
			"Truncated" : 0
		},
		{
			"Absolute Acceleration X" : 0.0085123563185334206,
			"Absolute Acceleration Y" : -0.013129138387739658,
			"Absolute Acceleration Z" : 0.00080441264435648918,
			"Absolute Velocity X" : 0.015550232492387295,
			"Absolute Velocity Y" : 0.0026804665103554726,
			"Absolute Velocity Z" : -0.00068826688220724463,
			"ActorName" : "CAR 76",
			"BoundingBox3D Extent X" : 4.0999999046325684,
			"BoundingBox3D Extent Y" : 1.4631067514419556,
			"BoundingBox3D Extent Z" : 1.4503613710403442,
			"BoundingBox3D Orientation Quat W" : 0.71024125814437866,
			"BoundingBox3D Orientation Quat X" : -0.01298220083117485,
			"BoundingBox3D Orientation Quat Y" : -0.010125180706381798,
			"BoundingBox3D Orientation Quat Z" : -0.70313990116119385,
			"BoundingBox3D Origin X" : 17.858982086181641,
			"BoundingBox3D Origin Y" : -22.914154052734375,
			"BoundingBox3D Origin Z" : 0.88764286041259766,
			"ObjectId" : 76,
			"ObjectType" : "CAR",
			"Occluded" : 0.0,
			"Relative Acceleration X" : 0.017410803586244583,
			"Relative Acceleration Y" : -0.016785398125648499,
			"Relative Acceleration Z" : 0.0071366610936820507,
			"Relative Velocity X" : 0.0080514512956142426,
			"Relative Velocity Y" : 0.0031240428797900677,
			"Relative Velocity Z" : -0.0017596536781638861,
			"Truncated" : 0
		},
		{
			"Absolute Acceleration X" : 0.059074092656373978,
			"Absolute Acceleration Y" : 0.011574159376323223,
			"Absolute Acceleration Z" : -0.01656535267829895,
			"Absolute Velocity X" : -0.14242501556873322,
			"Absolute Velocity Y" : 0.67012703418731689,
			"Absolute Velocity Z" : 0.0079450793564319611,
			"ActorName" : "PEDESTRIAN 77",
			"BoundingBox3D Extent X" : 0.52390921115875244,
			"BoundingBox3D Extent Y" : 0.72465044260025024,
			"BoundingBox3D Extent Z" : 1.5404287576675415,
			"BoundingBox3D Orientation Quat W" : 0.63996922969818115,
			"BoundingBox3D Orientation Quat X" : 0.0027767326682806015,
			"BoundingBox3D Orientation Quat Y" : 0.0074445675127208233,
			"BoundingBox3D Orientation Quat Z" : 0.76826304197311401,
			"BoundingBox3D Origin X" : 49.648128509521484,
			"BoundingBox3D Origin Y" : 12.32695198059082,
			"BoundingBox3D Origin Z" : 0.53180932998657227,
			"ObjectId" : 77,
			"ObjectType" : "PEDESTRIAN",
			"Occluded" : 0.0,
			"Relative Acceleration X" : 0.067108653485774994,
			"Relative Acceleration Y" : 0.010231295600533485,
			"Relative Acceleration Z" : -0.033127229660749435,
			"Relative Velocity X" : -0.1482684463262558,
			"Relative Velocity Y" : 0.66979128122329712,
			"Relative Velocity Z" : 0.0099431565031409264,
			"Truncated" : 0
		}
	],
	"FrameId" : 37388,
	"Timestamp" : 1676041324182067064,
	"TimestampMiddle" : 1676041324165067064
}